{"login/index.html":{"acl":{"owner":"system.user.admin","ownerGroup":"system.group.administrator","permissions":1632},"stats":{"size":30527},"mimeType":"text/html","binary":false,"modifiedAt":1641896432441},"login/favicon.ico":{"acl":{"owner":"system.user.admin","ownerGroup":"system.group.administrator","permissions":1632},"stats":{"size":16958},"mimeType":"image/x-icon","binary":true,"modifiedAt":1641896432501},"lib/js/translate.js":{"acl":{"owner":"system.user.admin","ownerGroup":"system.group.administrator","permissions":1632},"stats":{"size":3667},"mimeType":"application/javascript","binary":false,"modifiedAt":1641896432565},"lib/js/socket.io.js":{"acl":{"owner":"system.user.admin","ownerGroup":"system.group.administrator","permissions":1632},"stats":{"size":68657},"mimeType":"application/javascript","binary":false,"modifiedAt":1641896432621},"lib/js/showdown.min.js":{"acl":{"owner":"system.user.admin","ownerGroup":"system.group.administrator","permissions":1632},"stats":{"size":99094},"mimeType":"application/javascript","binary":false,"modifiedAt":1641896432677},"lib/js/selectID.js":{"acl":{"owner":"system.user.admin","ownerGroup":"system.group.administrator","permissions":1632},"stats":{"size":183747},"mimeType":"application/javascript","binary":false,"modifiedAt":1641896432734},"lib/js/materialize.js.map":{"acl":{"owner":"system.user.admin","ownerGroup":"system.group.administrator","permissions":1632},"stats":{"size":486127},"mimeType":"text/javascript","binary":false,"modifiedAt":1641896432799},"lib/js/materialize.js":{"acl":{"owner":"system.user.admin","ownerGroup":"system.group.administrator","permissions":1632},"stats":{"size":266871},"mimeType":"application/javascript","binary":false,"modifiedAt":1641896432866},"lib/js/loStorage.js":{"acl":{"owner":"system.user.admin","ownerGroup":"system.group.administrator","permissions":1632},"stats":{"size":2677},"mimeType":"application/javascript","binary":false,"modifiedAt":1641896432927},"lib/js/jquery.jqGrid-4.5.4.min.js":{"acl":{"owner":"system.user.admin","ownerGroup":"system.group.administrator","permissions":1632},"stats":{"size":269711},"mimeType":"application/javascript","binary":false,"modifiedAt":1641896432986},"lib/js/jquery.fancytree-all.min.js.map":{"acl":{"owner":"system.user.admin","ownerGroup":"system.group.administrator","permissions":1632},"stats":{"size":479146},"mimeType":"text/javascript","binary":false,"modifiedAt":1641896433052},"lib/js/jquery.fancytree-all.min.js":{"acl":{"owner":"system.user.admin","ownerGroup":"system.group.administrator","permissions":1632},"stats":{"size":75874},"mimeType":"application/javascript","binary":false,"modifiedAt":1641896433118},"lib/js/jquery-ui.min.js":{"acl":{"owner":"system.user.admin","ownerGroup":"system.group.administrator","permissions":1632},"stats":{"size":240422},"mimeType":"application/javascript","binary":false,"modifiedAt":1641896433232},"lib/js/jquery-ui.1.11.2.slider.min.js":{"acl":{"owner":"system.user.admin","ownerGroup":"system.group.administrator","permissions":1632},"stats":{"size":23703},"mimeType":"application/javascript","binary":false,"modifiedAt":1641896433291},"lib/js/jquery-ui-1.11.4.full.min.js":{"acl":{"owner":"system.user.admin","ownerGroup":"system.group.administrator","permissions":1632},"stats":{"size":240427},"mimeType":"application/javascript","binary":false,"modifiedAt":1641896433348},"lib/js/jquery-ui-1.11.3.full.min.js":{"acl":{"owner":"system.user.admin","ownerGroup":"system.group.administrator","permissions":1632},"stats":{"size":239564},"mimeType":"application/javascript","binary":false,"modifiedAt":1641896433407},"lib/js/jquery-ui-1.10.3.full.min.js":{"acl":{"owner":"system.user.admin","ownerGroup":"system.group.administrator","permissions":1632},"stats":{"size":228138},"mimeType":"application/javascript","binary":false,"modifiedAt":1641896433468},"lib/js/jquery-3.2.1.min.map":{"acl":{"owner":"system.user.admin","ownerGroup":"system.group.administrator","permissions":1632},"stats":{"size":131678},"mimeType":"text/javascript","binary":false,"modifiedAt":1641896433526},"lib/js/jquery-3.2.1.min.js":{"acl":{"owner":"system.user.admin","ownerGroup":"system.group.administrator","permissions":1632},"stats":{"size":86659},"mimeType":"application/javascript","binary":false,"modifiedAt":1641896433583},"lib/js/jquery-1.11.2.min.map":{"acl":{"owner":"system.user.admin","ownerGroup":"system.group.administrator","permissions":1632},"stats":{"size":142010},"mimeType":"text/javascript","binary":false,"modifiedAt":1641896433640},"lib/js/jquery-1.11.2.min.js":{"acl":{"owner":"system.user.admin","ownerGroup":"system.group.administrator","permissions":1632},"stats":{"size":95931},"mimeType":"application/javascript","binary":false,"modifiedAt":1641896433697},"lib/js/jquery-1.11.1.min.js":{"acl":{"owner":"system.user.admin","ownerGroup":"system.group.administrator","permissions":1632},"stats":{"size":95789},"mimeType":"application/javascript","binary":false,"modifiedAt":1641896433753},"lib/js/jquery-1.11.0.min.map":{"acl":{"owner":"system.user.admin","ownerGroup":"system.group.administrator","permissions":1632},"stats":{"size":142405},"mimeType":"text/javascript","binary":false,"modifiedAt":1641896433810},"lib/js/jquery-1.10.2.min.map":{"acl":{"owner":"system.user.admin","ownerGroup":"system.group.administrator","permissions":1632},"stats":{"size":140036},"mimeType":"text/javascript","binary":false,"modifiedAt":1641896433867},"lib/js/grid.locale-all.js":{"acl":{"owner":"system.user.admin","ownerGroup":"system.group.administrator","permissions":1632},"stats":{"size":27151},"mimeType":"application/javascript","binary":false,"modifiedAt":1641896433924},"lib/js/colResizable-1.6.min.js":{"acl":{"owner":"system.user.admin","ownerGroup":"system.group.administrator","permissions":1632},"stats":{"size":5817},"mimeType":"application/javascript","binary":false,"modifiedAt":1641896433985},"lib/js/colResizable-1.5.min.js":{"acl":{"owner":"system.user.admin","ownerGroup":"system.group.administrator","permissions":1632},"stats":{"size":5867},"mimeType":"application/javascript","binary":false,"modifiedAt":1641896434046},"lib/img/person.png":{"acl":{"owner":"system.user.admin","ownerGroup":"system.group.administrator","permissions":1632},"stats":{"size":3005},"mimeType":"image/png","binary":true,"modifiedAt":1641896434106},"lib/img/logo.png":{"acl":{"owner":"system.user.admin","ownerGroup":"system.group.administrator","permissions":1632},"stats":{"size":9376},"mimeType":"image/png","binary":true,"modifiedAt":1641896434166},"lib/img/favicon.ico":{"acl":{"owner":"system.user.admin","ownerGroup":"system.group.administrator","permissions":1632},"stats":{"size":16958},"mimeType":"image/x-icon","binary":true,"modifiedAt":1641896434226},"lib/css/themes/jquery-ui/vader/theme.css":{"acl":{"owner":"system.user.admin","ownerGroup":"system.group.administrator","permissions":1632},"stats":{"size":17118},"mimeType":"text/css","binary":false,"modifiedAt":1641896434287},"lib/css/themes/jquery-ui/vader/jquery-ui.min.css":{"acl":{"owner":"system.user.admin","ownerGroup":"system.group.administrator","permissions":1632},"stats":{"size":29840},"mimeType":"text/css","binary":false,"modifiedAt":1641896434350},"lib/css/themes/jquery-ui/vader/jquery-ui.css":{"acl":{"owner":"system.user.admin","ownerGroup":"system.group.administrator","permissions":1632},"stats":{"size":35046},"mimeType":"text/css","binary":false,"modifiedAt":1641896434411},"lib/css/themes/jquery-ui/vader/images/ui-icons_f29a00_256x240.png":{"acl":{"owner":"system.user.admin","ownerGroup":"system.group.administrator","permissions":1632},"stats":{"size":4599},"mimeType":"image/png","binary":true,"modifiedAt":1641896434474},"lib/css/themes/jquery-ui/vader/images/ui-icons_cd0a0a_256x240.png":{"acl":{"owner":"system.user.admin","ownerGroup":"system.group.administrator","permissions":1632},"stats":{"size":4599},"mimeType":"image/png","binary":true,"modifiedAt":1641896434535},"lib/css/themes/jquery-ui/vader/images/ui-icons_cccccc_256x240.png":{"acl":{"owner":"system.user.admin","ownerGroup":"system.group.administrator","permissions":1632},"stats":{"size":7015},"mimeType":"image/png","binary":true,"modifiedAt":1641896434595},"lib/css/themes/jquery-ui/vader/images/ui-icons_c98000_256x240.png":{"acl":{"owner":"system.user.admin","ownerGroup":"system.group.administrator","permissions":1632},"stats":{"size":4599},"mimeType":"image/png","binary":true,"modifiedAt":1641896434655},"lib/css/themes/jquery-ui/vader/images/ui-icons_bbbbbb_256x240.png":{"acl":{"owner":"system.user.admin","ownerGroup":"system.group.administrator","permissions":1632},"stats":{"size":7073},"mimeType":"image/png","binary":true,"modifiedAt":1641896434715},"lib/css/themes/jquery-ui/vader/images/ui-icons_aaaaaa_256x240.png":{"acl":{"owner":"system.user.admin","ownerGroup":"system.group.administrator","permissions":1632},"stats":{"size":7056},"mimeType":"image/png","binary":true,"modifiedAt":1641896434775},"lib/css/themes/jquery-ui/vader/images/ui-icons_666666_256x240.png":{"acl":{"owner":"system.user.admin","ownerGroup":"system.group.administrator","permissions":1632},"stats":{"size":7092},"mimeType":"image/png","binary":true,"modifiedAt":1641896434836},"lib/css/themes/jquery-ui/vader/images/ui-bg_inset-soft_15_121212_1x100.png":{"acl":{"owner":"system.user.admin","ownerGroup":"system.group.administrator","permissions":1632},"stats":{"size":316},"mimeType":"image/png","binary":true,"modifiedAt":1641896434898},"lib/css/themes/jquery-ui/vader/images/ui-bg_highlight-soft_60_dddddd_1x100.png":{"acl":{"owner":"system.user.admin","ownerGroup":"system.group.administrator","permissions":1632},"stats":{"size":318},"mimeType":"image/png","binary":true,"modifiedAt":1641896434957},"lib/css/themes/jquery-ui/vader/images/ui-bg_highlight-soft_35_adadad_1x100.png":{"acl":{"owner":"system.user.admin","ownerGroup":"system.group.administrator","permissions":1632},"stats":{"size":319},"mimeType":"image/png","binary":true,"modifiedAt":1641896435015},"lib/css/themes/jquery-ui/vader/images/ui-bg_highlight-hard_55_555555_1x100.png":{"acl":{"owner":"system.user.admin","ownerGroup":"system.group.administrator","permissions":1632},"stats":{"size":289},"mimeType":"image/png","binary":true,"modifiedAt":1641896435076},"lib/css/themes/jquery-ui/vader/images/ui-bg_highlight-hard_15_888888_1x100.png":{"acl":{"owner":"system.user.admin","ownerGroup":"system.group.administrator","permissions":1632},"stats":{"size":290},"mimeType":"image/png","binary":true,"modifiedAt":1641896435132},"lib/css/themes/jquery-ui/vader/images/ui-bg_gloss-wave_16_121212_500x100.png":{"acl":{"owner":"system.user.admin","ownerGroup":"system.group.administrator","permissions":1632},"stats":{"size":3887},"mimeType":"image/png","binary":true,"modifiedAt":1641896435188},"lib/css/themes/jquery-ui/vader/images/ui-bg_glass_95_fef1ec_1x400.png":{"acl":{"owner":"system.user.admin","ownerGroup":"system.group.administrator","permissions":1632},"stats":{"size":371},"mimeType":"image/png","binary":true,"modifiedAt":1641896435245},"lib/css/themes/jquery-ui/vader/images/ui-bg_flat_0_aaaaaa_40x100.png":{"acl":{"owner":"system.user.admin","ownerGroup":"system.group.administrator","permissions":1632},"stats":{"size":251},"mimeType":"image/png","binary":true,"modifiedAt":1641896435301},"lib/css/themes/jquery-ui/ui-lightness/theme.css":{"acl":{"owner":"system.user.admin","ownerGroup":"system.group.administrator","permissions":1632},"stats":{"size":17420},"mimeType":"text/css","binary":false,"modifiedAt":1641896435356},"lib/css/themes/jquery-ui/ui-lightness/jquery-ui.min.css":{"acl":{"owner":"system.user.admin","ownerGroup":"system.group.administrator","permissions":1632},"stats":{"size":30163},"mimeType":"text/css","binary":false,"modifiedAt":1641896435412},"lib/css/themes/jquery-ui/ui-lightness/jquery-ui.css":{"acl":{"owner":"system.user.admin","ownerGroup":"system.group.administrator","permissions":1632},"stats":{"size":35348},"mimeType":"text/css","binary":false,"modifiedAt":1641896435468},"lib/css/themes/jquery-ui/ui-lightness/images/ui-icons_ffffff_256x240.png":{"acl":{"owner":"system.user.admin","ownerGroup":"system.group.administrator","permissions":1632},"stats":{"size":6468},"mimeType":"image/png","binary":true,"modifiedAt":1641896435525},"lib/css/themes/jquery-ui/ui-lightness/images/ui-icons_ffd27a_256x240.png":{"acl":{"owner":"system.user.admin","ownerGroup":"system.group.administrator","permissions":1632},"stats":{"size":4599},"mimeType":"image/png","binary":true,"modifiedAt":1641896435581},"lib/css/themes/jquery-ui/ui-lightness/images/ui-icons_ef8c08_256x240.png":{"acl":{"owner":"system.user.admin","ownerGroup":"system.group.administrator","permissions":1632},"stats":{"size":4599},"mimeType":"image/png","binary":true,"modifiedAt":1641896435638},"lib/css/themes/jquery-ui/ui-lightness/images/ui-icons_228ef1_256x240.png":{"acl":{"owner":"system.user.admin","ownerGroup":"system.group.administrator","permissions":1632},"stats":{"size":4599},"mimeType":"image/png","binary":true,"modifiedAt":1641896435698},"lib/css/themes/jquery-ui/ui-lightness/images/ui-icons_222222_256x240.png":{"acl":{"owner":"system.user.admin","ownerGroup":"system.group.administrator","permissions":1632},"stats":{"size":7006},"mimeType":"image/png","binary":true,"modifiedAt":1641896435760},"lib/css/themes/jquery-ui/ui-lightness/images/ui-bg_highlight-soft_75_ffe45c_1x100.png":{"acl":{"owner":"system.user.admin","ownerGroup":"system.group.administrator","permissions":1632},"stats":{"size":367},"mimeType":"image/png","binary":true,"modifiedAt":1641896435954},"lib/css/themes/jquery-ui/ui-lightness/images/ui-bg_highlight-soft_100_eeeeee_1x100.png":{"acl":{"owner":"system.user.admin","ownerGroup":"system.group.administrator","permissions":1632},"stats":{"size":317},"mimeType":"image/png","binary":true,"modifiedAt":1641896436016},"lib/css/themes/jquery-ui/ui-lightness/images/ui-bg_gloss-wave_35_f6a828_500x100.png":{"acl":{"owner":"system.user.admin","ownerGroup":"system.group.administrator","permissions":1632},"stats":{"size":5854},"mimeType":"image/png","binary":true,"modifiedAt":1641896436072},"lib/css/themes/jquery-ui/ui-lightness/images/ui-bg_glass_65_ffffff_1x400.png":{"acl":{"owner":"system.user.admin","ownerGroup":"system.group.administrator","permissions":1632},"stats":{"size":246},"mimeType":"image/png","binary":true,"modifiedAt":1641896436128},"lib/css/themes/jquery-ui/ui-lightness/images/ui-bg_glass_100_fdf5ce_1x400.png":{"acl":{"owner":"system.user.admin","ownerGroup":"system.group.administrator","permissions":1632},"stats":{"size":387},"mimeType":"image/png","binary":true,"modifiedAt":1641896436183},"lib/css/themes/jquery-ui/ui-lightness/images/ui-bg_glass_100_f6f6f6_1x400.png":{"acl":{"owner":"system.user.admin","ownerGroup":"system.group.administrator","permissions":1632},"stats":{"size":301},"mimeType":"image/png","binary":true,"modifiedAt":1641896436240},"lib/css/themes/jquery-ui/ui-lightness/images/ui-bg_flat_10_000000_40x100.png":{"acl":{"owner":"system.user.admin","ownerGroup":"system.group.administrator","permissions":1632},"stats":{"size":244},"mimeType":"image/png","binary":true,"modifiedAt":1641896436298},"lib/css/themes/jquery-ui/ui-lightness/images/ui-bg_diagonals-thick_20_666666_40x40.png":{"acl":{"owner":"system.user.admin","ownerGroup":"system.group.administrator","permissions":1632},"stats":{"size":351},"mimeType":"image/png","binary":true,"modifiedAt":1641896436358},"lib/css/themes/jquery-ui/ui-lightness/images/ui-bg_diagonals-thick_18_b81900_40x40.png":{"acl":{"owner":"system.user.admin","ownerGroup":"system.group.administrator","permissions":1632},"stats":{"size":457},"mimeType":"image/png","binary":true,"modifiedAt":1641896436413},"lib/css/themes/jquery-ui/ui-darkness/theme.css":{"acl":{"owner":"system.user.admin","ownerGroup":"system.group.administrator","permissions":1632},"stats":{"size":17321},"mimeType":"text/css","binary":false,"modifiedAt":1641896436469},"lib/css/themes/jquery-ui/ui-darkness/jquery-ui.min.css":{"acl":{"owner":"system.user.admin","ownerGroup":"system.group.administrator","permissions":1632},"stats":{"size":30037},"mimeType":"text/css","binary":false,"modifiedAt":1641896436526},"lib/css/themes/jquery-ui/ui-darkness/jquery-ui.css":{"acl":{"owner":"system.user.admin","ownerGroup":"system.group.administrator","permissions":1632},"stats":{"size":35249},"mimeType":"text/css","binary":false,"modifiedAt":1641896436583},"lib/css/themes/jquery-ui/ui-darkness/images/ui-icons_ffffff_256x240.png":{"acl":{"owner":"system.user.admin","ownerGroup":"system.group.administrator","permissions":1632},"stats":{"size":6468},"mimeType":"image/png","binary":true,"modifiedAt":1641896436638},"lib/css/themes/jquery-ui/ui-darkness/images/ui-icons_cccccc_256x240.png":{"acl":{"owner":"system.user.admin","ownerGroup":"system.group.administrator","permissions":1632},"stats":{"size":7015},"mimeType":"image/png","binary":true,"modifiedAt":1641896436697},"lib/css/themes/jquery-ui/ui-darkness/images/ui-icons_a83300_256x240.png":{"acl":{"owner":"system.user.admin","ownerGroup":"system.group.administrator","permissions":1632},"stats":{"size":4599},"mimeType":"image/png","binary":true,"modifiedAt":1641896436758},"lib/css/themes/jquery-ui/ui-darkness/images/ui-icons_4b8e0b_256x240.png":{"acl":{"owner":"system.user.admin","ownerGroup":"system.group.administrator","permissions":1632},"stats":{"size":4599},"mimeType":"image/png","binary":true,"modifiedAt":1641896436824},"lib/css/themes/jquery-ui/ui-darkness/images/ui-icons_222222_256x240.png":{"acl":{"owner":"system.user.admin","ownerGroup":"system.group.administrator","permissions":1632},"stats":{"size":7006},"mimeType":"image/png","binary":true,"modifiedAt":1641896436885},"lib/css/themes/jquery-ui/ui-darkness/images/ui-bg_inset-soft_30_f58400_1x100.png":{"acl":{"owner":"system.user.admin","ownerGroup":"system.group.administrator","permissions":1632},"stats":{"size":379},"mimeType":"image/png","binary":true,"modifiedAt":1641896436945},"lib/css/themes/jquery-ui/ui-darkness/images/ui-bg_inset-soft_25_000000_1x100.png":{"acl":{"owner":"system.user.admin","ownerGroup":"system.group.administrator","permissions":1632},"stats":{"size":314},"mimeType":"image/png","binary":true,"modifiedAt":1641896437006},"lib/css/themes/jquery-ui/ui-darkness/images/ui-bg_highlight-soft_80_eeeeee_1x100.png":{"acl":{"owner":"system.user.admin","ownerGroup":"system.group.administrator","permissions":1632},"stats":{"size":315},"mimeType":"image/png","binary":true,"modifiedAt":1641896437068},"lib/css/themes/jquery-ui/ui-darkness/images/ui-bg_gloss-wave_25_333333_500x100.png":{"acl":{"owner":"system.user.admin","ownerGroup":"system.group.administrator","permissions":1632},"stats":{"size":3855},"mimeType":"image/png","binary":true,"modifiedAt":1641896437128},"lib/css/themes/jquery-ui/ui-darkness/images/ui-bg_glass_40_ffc73d_1x400.png":{"acl":{"owner":"system.user.admin","ownerGroup":"system.group.administrator","permissions":1632},"stats":{"size":355},"mimeType":"image/png","binary":true,"modifiedAt":1641896437189},"lib/css/themes/jquery-ui/ui-darkness/images/ui-bg_glass_40_0078a3_1x400.png":{"acl":{"owner":"system.user.admin","ownerGroup":"system.group.administrator","permissions":1632},"stats":{"size":381},"mimeType":"image/png","binary":true,"modifiedAt":1641896437250},"lib/css/themes/jquery-ui/ui-darkness/images/ui-bg_glass_20_555555_1x400.png":{"acl":{"owner":"system.user.admin","ownerGroup":"system.group.administrator","permissions":1632},"stats":{"size":299},"mimeType":"image/png","binary":true,"modifiedAt":1641896437311},"lib/css/themes/jquery-ui/ui-darkness/images/ui-bg_flat_50_5c5c5c_40x100.png":{"acl":{"owner":"system.user.admin","ownerGroup":"system.group.administrator","permissions":1632},"stats":{"size":269},"mimeType":"image/png","binary":true,"modifiedAt":1641896437372},"lib/css/themes/jquery-ui/ui-darkness/images/ui-bg_flat_30_cccccc_40x100.png":{"acl":{"owner":"system.user.admin","ownerGroup":"system.group.administrator","permissions":1632},"stats":{"size":259},"mimeType":"image/png","binary":true,"modifiedAt":1641896437434},"lib/css/themes/jquery-ui/sunny/theme.css":{"acl":{"owner":"system.user.admin","ownerGroup":"system.group.administrator","permissions":1632},"stats":{"size":17366},"mimeType":"text/css","binary":false,"modifiedAt":1641896437499},"lib/css/themes/jquery-ui/sunny/jquery-ui.min.css":{"acl":{"owner":"system.user.admin","ownerGroup":"system.group.administrator","permissions":1632},"stats":{"size":30127},"mimeType":"text/css","binary":false,"modifiedAt":1641896437562},"lib/css/themes/jquery-ui/sunny/jquery-ui.css":{"acl":{"owner":"system.user.admin","ownerGroup":"system.group.administrator","permissions":1632},"stats":{"size":35294},"mimeType":"text/css","binary":false,"modifiedAt":1641896437623},"lib/css/themes/jquery-ui/sunny/images/ui-icons_ffe180_256x240.png":{"acl":{"owner":"system.user.admin","ownerGroup":"system.group.administrator","permissions":1632},"stats":{"size":4599},"mimeType":"image/png","binary":true,"modifiedAt":1641896437684},"lib/css/themes/jquery-ui/sunny/images/ui-icons_fadc7a_256x240.png":{"acl":{"owner":"system.user.admin","ownerGroup":"system.group.administrator","permissions":1632},"stats":{"size":4599},"mimeType":"image/png","binary":true,"modifiedAt":1641896437747},"lib/css/themes/jquery-ui/sunny/images/ui-icons_ed9f26_256x240.png":{"acl":{"owner":"system.user.admin","ownerGroup":"system.group.administrator","permissions":1632},"stats":{"size":4599},"mimeType":"image/png","binary":true,"modifiedAt":1641896437808},"lib/css/themes/jquery-ui/sunny/images/ui-icons_eb990f_256x240.png":{"acl":{"owner":"system.user.admin","ownerGroup":"system.group.administrator","permissions":1632},"stats":{"size":4599},"mimeType":"image/png","binary":true,"modifiedAt":1641896437871},"lib/css/themes/jquery-ui/sunny/images/ui-icons_d19405_256x240.png":{"acl":{"owner":"system.user.admin","ownerGroup":"system.group.administrator","permissions":1632},"stats":{"size":4599},"mimeType":"image/png","binary":true,"modifiedAt":1641896437932},"lib/css/themes/jquery-ui/sunny/images/ui-icons_bd7b00_256x240.png":{"acl":{"owner":"system.user.admin","ownerGroup":"system.group.administrator","permissions":1632},"stats":{"size":4599},"mimeType":"image/png","binary":true,"modifiedAt":1641896437993},"lib/css/themes/jquery-ui/sunny/images/ui-icons_3d3d3d_256x240.png":{"acl":{"owner":"system.user.admin","ownerGroup":"system.group.administrator","permissions":1632},"stats":{"size":7055},"mimeType":"image/png","binary":true,"modifiedAt":1641896438057},"lib/css/themes/jquery-ui/sunny/images/ui-bg_inset-soft_30_ffffff_1x100.png":{"acl":{"owner":"system.user.admin","ownerGroup":"system.group.administrator","permissions":1632},"stats":{"size":242},"mimeType":"image/png","binary":true,"modifiedAt":1641896438118},"lib/css/themes/jquery-ui/sunny/images/ui-bg_highlight-soft_100_feeebd_1x100.png":{"acl":{"owner":"system.user.admin","ownerGroup":"system.group.administrator","permissions":1632},"stats":{"size":382},"mimeType":"image/png","binary":true,"modifiedAt":1641896438182},"lib/css/themes/jquery-ui/sunny/images/ui-bg_gloss-wave_90_fff9e5_500x100.png":{"acl":{"owner":"system.user.admin","ownerGroup":"system.group.administrator","permissions":1632},"stats":{"size":5428},"mimeType":"image/png","binary":true,"modifiedAt":1641896438242},"lib/css/themes/jquery-ui/sunny/images/ui-bg_gloss-wave_70_ffdd57_500x100.png":{"acl":{"owner":"system.user.admin","ownerGroup":"system.group.administrator","permissions":1632},"stats":{"size":5582},"mimeType":"image/png","binary":true,"modifiedAt":1641896438304},"lib/css/themes/jquery-ui/sunny/images/ui-bg_gloss-wave_60_fece2f_500x100.png":{"acl":{"owner":"system.user.admin","ownerGroup":"system.group.administrator","permissions":1632},"stats":{"size":5889},"mimeType":"image/png","binary":true,"modifiedAt":1641896438372},"lib/css/themes/jquery-ui/sunny/images/ui-bg_gloss-wave_45_817865_500x100.png":{"acl":{"owner":"system.user.admin","ownerGroup":"system.group.administrator","permissions":1632},"stats":{"size":5929},"mimeType":"image/png","binary":true,"modifiedAt":1641896438437},"lib/css/themes/jquery-ui/sunny/images/ui-bg_flat_50_5c5c5c_40x100.png":{"acl":{"owner":"system.user.admin","ownerGroup":"system.group.administrator","permissions":1632},"stats":{"size":269},"mimeType":"image/png","binary":true,"modifiedAt":1641896438507},"lib/css/themes/jquery-ui/sunny/images/ui-bg_flat_30_cccccc_40x100.png":{"acl":{"owner":"system.user.admin","ownerGroup":"system.group.administrator","permissions":1632},"stats":{"size":259},"mimeType":"image/png","binary":true,"modifiedAt":1641896438572},"lib/css/themes/jquery-ui/sunny/images/ui-bg_diagonals-medium_20_d34d17_40x40.png":{"acl":{"owner":"system.user.admin","ownerGroup":"system.group.administrator","permissions":1632},"stats":{"size":421},"mimeType":"image/png","binary":true,"modifiedAt":1641896438633},"lib/css/themes/jquery-ui/start/theme.css":{"acl":{"owner":"system.user.admin","ownerGroup":"system.group.administrator","permissions":1632},"stats":{"size":17319},"mimeType":"text/css","binary":false,"modifiedAt":1641896438696},"lib/css/themes/jquery-ui/start/jquery-ui.min.css":{"acl":{"owner":"system.user.admin","ownerGroup":"system.group.administrator","permissions":1632},"stats":{"size":30066},"mimeType":"text/css","binary":false,"modifiedAt":1641896438757},"lib/css/themes/jquery-ui/start/jquery-ui.css":{"acl":{"owner":"system.user.admin","ownerGroup":"system.group.administrator","permissions":1632},"stats":{"size":35247},"mimeType":"text/css","binary":false,"modifiedAt":1641896438818},"lib/css/themes/jquery-ui/start/images/ui-icons_fcd113_256x240.png":{"acl":{"owner":"system.user.admin","ownerGroup":"system.group.administrator","permissions":1632},"stats":{"size":4599},"mimeType":"image/png","binary":true,"modifiedAt":1641896438880},"lib/css/themes/jquery-ui/start/images/ui-icons_f7a50d_256x240.png":{"acl":{"owner":"system.user.admin","ownerGroup":"system.group.administrator","permissions":1632},"stats":{"size":4599},"mimeType":"image/png","binary":true,"modifiedAt":1641896438941},"lib/css/themes/jquery-ui/start/images/ui-icons_f5e175_256x240.png":{"acl":{"owner":"system.user.admin","ownerGroup":"system.group.administrator","permissions":1632},"stats":{"size":4599},"mimeType":"image/png","binary":true,"modifiedAt":1641896439002},"lib/css/themes/jquery-ui/start/images/ui-icons_e0fdff_256x240.png":{"acl":{"owner":"system.user.admin","ownerGroup":"system.group.administrator","permissions":1632},"stats":{"size":4599},"mimeType":"image/png","binary":true,"modifiedAt":1641896439065},"lib/css/themes/jquery-ui/start/images/ui-icons_d8e7f3_256x240.png":{"acl":{"owner":"system.user.admin","ownerGroup":"system.group.administrator","permissions":1632},"stats":{"size":4599},"mimeType":"image/png","binary":true,"modifiedAt":1641896439130},"lib/css/themes/jquery-ui/start/images/ui-icons_056b93_256x240.png":{"acl":{"owner":"system.user.admin","ownerGroup":"system.group.administrator","permissions":1632},"stats":{"size":4599},"mimeType":"image/png","binary":true,"modifiedAt":1641896439189},"lib/css/themes/jquery-ui/start/images/ui-icons_0078ae_256x240.png":{"acl":{"owner":"system.user.admin","ownerGroup":"system.group.administrator","permissions":1632},"stats":{"size":4599},"mimeType":"image/png","binary":true,"modifiedAt":1641896439253},"lib/css/themes/jquery-ui/start/images/ui-bg_inset-hard_100_fcfdfd_1x100.png":{"acl":{"owner":"system.user.admin","ownerGroup":"system.group.administrator","permissions":1632},"stats":{"size":331},"mimeType":"image/png","binary":true,"modifiedAt":1641896439313},"lib/css/themes/jquery-ui/start/images/ui-bg_gloss-wave_75_2191c0_500x100.png":{"acl":{"owner":"system.user.admin","ownerGroup":"system.group.administrator","permissions":1632},"stats":{"size":6016},"mimeType":"image/png","binary":true,"modifiedAt":1641896439375},"lib/css/themes/jquery-ui/start/images/ui-bg_gloss-wave_50_6eac2c_500x100.png":{"acl":{"owner":"system.user.admin","ownerGroup":"system.group.administrator","permissions":1632},"stats":{"size":5945},"mimeType":"image/png","binary":true,"modifiedAt":1641896439439},"lib/css/themes/jquery-ui/start/images/ui-bg_gloss-wave_45_e14f1c_500x100.png":{"acl":{"owner":"system.user.admin","ownerGroup":"system.group.administrator","permissions":1632},"stats":{"size":5903},"mimeType":"image/png","binary":true,"modifiedAt":1641896439497},"lib/css/themes/jquery-ui/start/images/ui-bg_glass_75_79c9ec_1x400.png":{"acl":{"owner":"system.user.admin","ownerGroup":"system.group.administrator","permissions":1632},"stats":{"size":387},"mimeType":"image/png","binary":true,"modifiedAt":1641896439558},"lib/css/themes/jquery-ui/start/images/ui-bg_glass_55_f8da4e_1x400.png":{"acl":{"owner":"system.user.admin","ownerGroup":"system.group.administrator","permissions":1632},"stats":{"size":384},"mimeType":"image/png","binary":true,"modifiedAt":1641896439618},"lib/css/themes/jquery-ui/start/images/ui-bg_glass_45_0078ae_1x400.png":{"acl":{"owner":"system.user.admin","ownerGroup":"system.group.administrator","permissions":1632},"stats":{"size":385},"mimeType":"image/png","binary":true,"modifiedAt":1641896439678},"lib/css/themes/jquery-ui/start/images/ui-bg_flat_75_aaaaaa_40x100.png":{"acl":{"owner":"system.user.admin","ownerGroup":"system.group.administrator","permissions":1632},"stats":{"size":251},"mimeType":"image/png","binary":true,"modifiedAt":1641896439739},"lib/css/themes/jquery-ui/start/images/ui-bg_flat_55_999999_40x100.png":{"acl":{"owner":"system.user.admin","ownerGroup":"system.group.administrator","permissions":1632},"stats":{"size":259},"mimeType":"image/png","binary":true,"modifiedAt":1641896439803},"lib/css/themes/jquery-ui/smoothness/theme.css":{"acl":{"owner":"system.user.admin","ownerGroup":"system.group.administrator","permissions":1632},"stats":{"size":17284},"mimeType":"text/css","binary":false,"modifiedAt":1641896439867},"lib/css/themes/jquery-ui/smoothness/jquery-ui.min.css":{"acl":{"owner":"system.user.admin","ownerGroup":"system.group.administrator","permissions":1632},"stats":{"size":30021},"mimeType":"text/css","binary":false,"modifiedAt":1641896439929},"lib/css/themes/jquery-ui/smoothness/jquery-ui.css":{"acl":{"owner":"system.user.admin","ownerGroup":"system.group.administrator","permissions":1632},"stats":{"size":35212},"mimeType":"text/css","binary":false,"modifiedAt":1641896439991},"lib/css/themes/jquery-ui/smoothness/images/ui-icons_cd0a0a_256x240.png":{"acl":{"owner":"system.user.admin","ownerGroup":"system.group.administrator","permissions":1632},"stats":{"size":4599},"mimeType":"image/png","binary":true,"modifiedAt":1641896440053},"lib/css/themes/jquery-ui/smoothness/images/ui-icons_888888_256x240.png":{"acl":{"owner":"system.user.admin","ownerGroup":"system.group.administrator","permissions":1632},"stats":{"size":7092},"mimeType":"image/png","binary":true,"modifiedAt":1641896440129},"lib/css/themes/jquery-ui/smoothness/images/ui-icons_454545_256x240.png":{"acl":{"owner":"system.user.admin","ownerGroup":"system.group.administrator","permissions":1632},"stats":{"size":7071},"mimeType":"image/png","binary":true,"modifiedAt":1641896440192},"lib/css/themes/jquery-ui/smoothness/images/ui-icons_2e83ff_256x240.png":{"acl":{"owner":"system.user.admin","ownerGroup":"system.group.administrator","permissions":1632},"stats":{"size":4599},"mimeType":"image/png","binary":true,"modifiedAt":1641896440253},"lib/css/themes/jquery-ui/smoothness/images/ui-icons_222222_256x240.png":{"acl":{"owner":"system.user.admin","ownerGroup":"system.group.administrator","permissions":1632},"stats":{"size":7006},"mimeType":"image/png","binary":true,"modifiedAt":1641896440313},"lib/css/themes/jquery-ui/smoothness/images/ui-bg_highlight-soft_75_cccccc_1x100.png":{"acl":{"owner":"system.user.admin","ownerGroup":"system.group.administrator","permissions":1632},"stats":{"size":319},"mimeType":"image/png","binary":true,"modifiedAt":1641896440374},"lib/css/themes/jquery-ui/smoothness/images/ui-bg_glass_95_fef1ec_1x400.png":{"acl":{"owner":"system.user.admin","ownerGroup":"system.group.administrator","permissions":1632},"stats":{"size":371},"mimeType":"image/png","binary":true,"modifiedAt":1641896440436},"lib/css/themes/jquery-ui/smoothness/images/ui-bg_glass_75_e6e6e6_1x400.png":{"acl":{"owner":"system.user.admin","ownerGroup":"system.group.administrator","permissions":1632},"stats":{"size":301},"mimeType":"image/png","binary":true,"modifiedAt":1641896440498},"lib/css/themes/jquery-ui/smoothness/images/ui-bg_glass_75_dadada_1x400.png":{"acl":{"owner":"system.user.admin","ownerGroup":"system.group.administrator","permissions":1632},"stats":{"size":301},"mimeType":"image/png","binary":true,"modifiedAt":1641896440560},"lib/css/themes/jquery-ui/smoothness/images/ui-bg_glass_65_ffffff_1x400.png":{"acl":{"owner":"system.user.admin","ownerGroup":"system.group.administrator","permissions":1632},"stats":{"size":246},"mimeType":"image/png","binary":true,"modifiedAt":1641896440623},"lib/css/themes/jquery-ui/smoothness/images/ui-bg_glass_55_fbf9ee_1x400.png":{"acl":{"owner":"system.user.admin","ownerGroup":"system.group.administrator","permissions":1632},"stats":{"size":374},"mimeType":"image/png","binary":true,"modifiedAt":1641896440684},"lib/css/themes/jquery-ui/smoothness/images/ui-bg_flat_75_ffffff_40x100.png":{"acl":{"owner":"system.user.admin","ownerGroup":"system.group.administrator","permissions":1632},"stats":{"size":247},"mimeType":"image/png","binary":true,"modifiedAt":1641896440746},"lib/css/themes/jquery-ui/smoothness/images/ui-bg_flat_0_aaaaaa_40x100.png":{"acl":{"owner":"system.user.admin","ownerGroup":"system.group.administrator","permissions":1632},"stats":{"size":251},"mimeType":"image/png","binary":true,"modifiedAt":1641896440808},"lib/css/themes/jquery-ui/redmond/jquery.ui.theme.css":{"acl":{"owner":"system.user.admin","ownerGroup":"system.group.administrator","permissions":1632},"stats":{"size":17551},"mimeType":"text/css","binary":false,"modifiedAt":1641896440870},"lib/css/themes/jquery-ui/redmond/jquery-ui.min.css":{"acl":{"owner":"system.user.admin","ownerGroup":"system.group.administrator","permissions":1632},"stats":{"size":30121},"mimeType":"text/css","binary":false,"modifiedAt":1641896440932},"lib/css/themes/jquery-ui/redmond/jquery-ui.css":{"acl":{"owner":"system.user.admin","ownerGroup":"system.group.administrator","permissions":1632},"stats":{"size":35285},"mimeType":"text/css","binary":false,"modifiedAt":1641896440994},"lib/css/themes/jquery-ui/redmond/images/ui-icons_f9bd01_256x240.png":{"acl":{"owner":"system.user.admin","ownerGroup":"system.group.administrator","permissions":1632},"stats":{"size":4599},"mimeType":"image/png","binary":true,"modifiedAt":1641896441057},"lib/css/themes/jquery-ui/redmond/images/ui-icons_d8e7f3_256x240.png":{"acl":{"owner":"system.user.admin","ownerGroup":"system.group.administrator","permissions":1632},"stats":{"size":4599},"mimeType":"image/png","binary":true,"modifiedAt":1641896441117},"lib/css/themes/jquery-ui/redmond/images/ui-icons_cd0a0a_256x240.png":{"acl":{"owner":"system.user.admin","ownerGroup":"system.group.administrator","permissions":1632},"stats":{"size":4599},"mimeType":"image/png","binary":true,"modifiedAt":1641896441178},"lib/css/themes/jquery-ui/redmond/images/ui-icons_6da8d5_256x240.png":{"acl":{"owner":"system.user.admin","ownerGroup":"system.group.administrator","permissions":1632},"stats":{"size":4599},"mimeType":"image/png","binary":true,"modifiedAt":1641896441238},"lib/css/themes/jquery-ui/redmond/images/ui-icons_469bdd_256x240.png":{"acl":{"owner":"system.user.admin","ownerGroup":"system.group.administrator","permissions":1632},"stats":{"size":4599},"mimeType":"image/png","binary":true,"modifiedAt":1641896441300},"lib/css/themes/jquery-ui/redmond/images/ui-icons_2e83ff_256x240.png":{"acl":{"owner":"system.user.admin","ownerGroup":"system.group.administrator","permissions":1632},"stats":{"size":4599},"mimeType":"image/png","binary":true,"modifiedAt":1641896441362},"lib/css/themes/jquery-ui/redmond/images/ui-icons_217bc0_256x240.png":{"acl":{"owner":"system.user.admin","ownerGroup":"system.group.administrator","permissions":1632},"stats":{"size":4599},"mimeType":"image/png","binary":true,"modifiedAt":1641896441424},"lib/css/themes/jquery-ui/redmond/images/ui-bg_inset-hard_100_fcfdfd_1x100.png":{"acl":{"owner":"system.user.admin","ownerGroup":"system.group.administrator","permissions":1632},"stats":{"size":331},"mimeType":"image/png","binary":true,"modifiedAt":1641896441486},"lib/css/themes/jquery-ui/redmond/images/ui-bg_inset-hard_100_f5f8f9_1x100.png":{"acl":{"owner":"system.user.admin","ownerGroup":"system.group.administrator","permissions":1632},"stats":{"size":372},"mimeType":"image/png","binary":true,"modifiedAt":1641896441558},"lib/css/themes/jquery-ui/redmond/images/ui-bg_gloss-wave_55_5c9ccc_500x100.png":{"acl":{"owner":"system.user.admin","ownerGroup":"system.group.administrator","permissions":1632},"stats":{"size":5863},"mimeType":"image/png","binary":true,"modifiedAt":1641896441618},"lib/css/themes/jquery-ui/redmond/images/ui-bg_glass_95_fef1ec_1x400.png":{"acl":{"owner":"system.user.admin","ownerGroup":"system.group.administrator","permissions":1632},"stats":{"size":371},"mimeType":"image/png","binary":true,"modifiedAt":1641896441681},"lib/css/themes/jquery-ui/redmond/images/ui-bg_glass_85_dfeffc_1x400.png":{"acl":{"owner":"system.user.admin","ownerGroup":"system.group.administrator","permissions":1632},"stats":{"size":380},"mimeType":"image/png","binary":true,"modifiedAt":1641896441742},"lib/css/themes/jquery-ui/redmond/images/ui-bg_glass_75_d0e5f5_1x400.png":{"acl":{"owner":"system.user.admin","ownerGroup":"system.group.administrator","permissions":1632},"stats":{"size":375},"mimeType":"image/png","binary":true,"modifiedAt":1641896441803},"lib/css/themes/jquery-ui/redmond/images/ui-bg_flat_55_fbec88_40x100.png":{"acl":{"owner":"system.user.admin","ownerGroup":"system.group.administrator","permissions":1632},"stats":{"size":261},"mimeType":"image/png","binary":true,"modifiedAt":1641896441863},"lib/css/themes/jquery-ui/redmond/images/ui-bg_flat_0_aaaaaa_40x100.png":{"acl":{"owner":"system.user.admin","ownerGroup":"system.group.administrator","permissions":1632},"stats":{"size":251},"mimeType":"image/png","binary":true,"modifiedAt":1641896441926},"lib/css/themes/jquery-ui/redmond/images/animated-overlay.gif":{"acl":{"owner":"system.user.admin","ownerGroup":"system.group.administrator","permissions":1632},"stats":{"size":1738},"mimeType":"image/gif","binary":true,"modifiedAt":1641896441989},"lib/css/themes/jquery-ui/overcast/theme.css":{"acl":{"owner":"system.user.admin","ownerGroup":"system.group.administrator","permissions":1632},"stats":{"size":17331},"mimeType":"text/css","binary":false,"modifiedAt":1641896442050},"lib/css/themes/jquery-ui/overcast/jquery-ui.min.css":{"acl":{"owner":"system.user.admin","ownerGroup":"system.group.administrator","permissions":1632},"stats":{"size":30042},"mimeType":"text/css","binary":false,"modifiedAt":1641896442111},"lib/css/themes/jquery-ui/overcast/jquery-ui.css":{"acl":{"owner":"system.user.admin","ownerGroup":"system.group.administrator","permissions":1632},"stats":{"size":35259},"mimeType":"text/css","binary":false,"modifiedAt":1641896442174},"lib/css/themes/jquery-ui/overcast/images/ui-icons_fbc856_256x240.png":{"acl":{"owner":"system.user.admin","ownerGroup":"system.group.administrator","permissions":1632},"stats":{"size":4599},"mimeType":"image/png","binary":true,"modifiedAt":1641896442235},"lib/css/themes/jquery-ui/overcast/images/ui-icons_999999_256x240.png":{"acl":{"owner":"system.user.admin","ownerGroup":"system.group.administrator","permissions":1632},"stats":{"size":7092},"mimeType":"image/png","binary":true,"modifiedAt":1641896442297},"lib/css/themes/jquery-ui/overcast/images/ui-icons_70b2e1_256x240.png":{"acl":{"owner":"system.user.admin","ownerGroup":"system.group.administrator","permissions":1632},"stats":{"size":4599},"mimeType":"image/png","binary":true,"modifiedAt":1641896442358},"lib/css/themes/jquery-ui/overcast/images/ui-icons_454545_256x240.png":{"acl":{"owner":"system.user.admin","ownerGroup":"system.group.administrator","permissions":1632},"stats":{"size":7071},"mimeType":"image/png","binary":true,"modifiedAt":1641896442419},"lib/css/themes/jquery-ui/overcast/images/ui-icons_3383bb_256x240.png":{"acl":{"owner":"system.user.admin","ownerGroup":"system.group.administrator","permissions":1632},"stats":{"size":4599},"mimeType":"image/png","binary":true,"modifiedAt":1641896442482},"lib/css/themes/jquery-ui/overcast/images/ui-bg_inset-soft_50_c9c9c9_1x100.png":{"acl":{"owner":"system.user.admin","ownerGroup":"system.group.administrator","permissions":1632},"stats":{"size":320},"mimeType":"image/png","binary":true,"modifiedAt":1641896442545},"lib/css/themes/jquery-ui/overcast/images/ui-bg_inset-hard_75_999999_1x100.png":{"acl":{"owner":"system.user.admin","ownerGroup":"system.group.administrator","permissions":1632},"stats":{"size":292},"mimeType":"image/png","binary":true,"modifiedAt":1641896442606},"lib/css/themes/jquery-ui/overcast/images/ui-bg_glass_60_eeeeee_1x400.png":{"acl":{"owner":"system.user.admin","ownerGroup":"system.group.administrator","permissions":1632},"stats":{"size":301},"mimeType":"image/png","binary":true,"modifiedAt":1641896442668},"lib/css/themes/jquery-ui/overcast/images/ui-bg_glass_35_dddddd_1x400.png":{"acl":{"owner":"system.user.admin","ownerGroup":"system.group.administrator","permissions":1632},"stats":{"size":301},"mimeType":"image/png","binary":true,"modifiedAt":1641896442733},"lib/css/themes/jquery-ui/overcast/images/ui-bg_glass_100_f8f8f8_1x400.png":{"acl":{"owner":"system.user.admin","ownerGroup":"system.group.administrator","permissions":1632},"stats":{"size":301},"mimeType":"image/png","binary":true,"modifiedAt":1641896442794},"lib/css/themes/jquery-ui/overcast/images/ui-bg_flat_55_eeeeee_40x100.png":{"acl":{"owner":"system.user.admin","ownerGroup":"system.group.administrator","permissions":1632},"stats":{"size":259},"mimeType":"image/png","binary":true,"modifiedAt":1641896442856},"lib/css/themes/jquery-ui/overcast/images/ui-bg_flat_55_c0402a_40x100.png":{"acl":{"owner":"system.user.admin","ownerGroup":"system.group.administrator","permissions":1632},"stats":{"size":261},"mimeType":"image/png","binary":true,"modifiedAt":1641896442918},"lib/css/themes/jquery-ui/overcast/images/ui-bg_flat_0_eeeeee_40x100.png":{"acl":{"owner":"system.user.admin","ownerGroup":"system.group.administrator","permissions":1632},"stats":{"size":259},"mimeType":"image/png","binary":true,"modifiedAt":1641896442980},"lib/css/themes/jquery-ui/overcast/images/ui-bg_flat_0_aaaaaa_40x100.png":{"acl":{"owner":"system.user.admin","ownerGroup":"system.group.administrator","permissions":1632},"stats":{"size":251},"mimeType":"image/png","binary":true,"modifiedAt":1641896443043},"lib/css/themes/jquery-ui/humanity/theme.css":{"acl":{"owner":"system.user.admin","ownerGroup":"system.group.administrator","permissions":1632},"stats":{"size":17350},"mimeType":"text/css","binary":false,"modifiedAt":1641896443106},"lib/css/themes/jquery-ui/humanity/jquery-ui.min.css":{"acl":{"owner":"system.user.admin","ownerGroup":"system.group.administrator","permissions":1632},"stats":{"size":30120},"mimeType":"text/css","binary":false,"modifiedAt":1641896443168},"lib/css/themes/jquery-ui/humanity/jquery-ui.css":{"acl":{"owner":"system.user.admin","ownerGroup":"system.group.administrator","permissions":1632},"stats":{"size":35278},"mimeType":"text/css","binary":false,"modifiedAt":1641896443229},"lib/css/themes/jquery-ui/humanity/images/ui-icons_ffffff_256x240.png":{"acl":{"owner":"system.user.admin","ownerGroup":"system.group.administrator","permissions":1632},"stats":{"size":6468},"mimeType":"image/png","binary":true,"modifiedAt":1641896443290},"lib/css/themes/jquery-ui/humanity/images/ui-icons_ff7519_256x240.png":{"acl":{"owner":"system.user.admin","ownerGroup":"system.group.administrator","permissions":1632},"stats":{"size":4599},"mimeType":"image/png","binary":true,"modifiedAt":1641896443353},"lib/css/themes/jquery-ui/humanity/images/ui-icons_f35f07_256x240.png":{"acl":{"owner":"system.user.admin","ownerGroup":"system.group.administrator","permissions":1632},"stats":{"size":4599},"mimeType":"image/png","binary":true,"modifiedAt":1641896443422},"lib/css/themes/jquery-ui/humanity/images/ui-icons_f08000_256x240.png":{"acl":{"owner":"system.user.admin","ownerGroup":"system.group.administrator","permissions":1632},"stats":{"size":4599},"mimeType":"image/png","binary":true,"modifiedAt":1641896443503},"lib/css/themes/jquery-ui/humanity/images/ui-icons_cb672b_256x240.png":{"acl":{"owner":"system.user.admin","ownerGroup":"system.group.administrator","permissions":1632},"stats":{"size":4599},"mimeType":"image/png","binary":true,"modifiedAt":1641896443563},"lib/css/themes/jquery-ui/humanity/images/ui-icons_c47a23_256x240.png":{"acl":{"owner":"system.user.admin","ownerGroup":"system.group.administrator","permissions":1632},"stats":{"size":4599},"mimeType":"image/png","binary":true,"modifiedAt":1641896443622},"lib/css/themes/jquery-ui/humanity/images/ui-bg_inset-soft_100_f4f0ec_1x100.png":{"acl":{"owner":"system.user.admin","ownerGroup":"system.group.administrator","permissions":1632},"stats":{"size":442},"mimeType":"image/png","binary":true,"modifiedAt":1641896443685},"lib/css/themes/jquery-ui/humanity/images/ui-bg_highlight-hard_75_f5f5b5_1x100.png":{"acl":{"owner":"system.user.admin","ownerGroup":"system.group.administrator","permissions":1632},"stats":{"size":362},"mimeType":"image/png","binary":true,"modifiedAt":1641896443750},"lib/css/themes/jquery-ui/humanity/images/ui-bg_highlight-hard_65_fee4bd_1x100.png":{"acl":{"owner":"system.user.admin","ownerGroup":"system.group.administrator","permissions":1632},"stats":{"size":353},"mimeType":"image/png","binary":true,"modifiedAt":1641896443813},"lib/css/themes/jquery-ui/humanity/images/ui-bg_highlight-hard_100_f4f0ec_1x100.png":{"acl":{"owner":"system.user.admin","ownerGroup":"system.group.administrator","permissions":1632},"stats":{"size":366},"mimeType":"image/png","binary":true,"modifiedAt":1641896443874},"lib/css/themes/jquery-ui/humanity/images/ui-bg_glass_70_ede4d4_1x400.png":{"acl":{"owner":"system.user.admin","ownerGroup":"system.group.administrator","permissions":1632},"stats":{"size":393},"mimeType":"image/png","binary":true,"modifiedAt":1641896443936},"lib/css/themes/jquery-ui/humanity/images/ui-bg_glass_25_cb842e_1x400.png":{"acl":{"owner":"system.user.admin","ownerGroup":"system.group.administrator","permissions":1632},"stats":{"size":374},"mimeType":"image/png","binary":true,"modifiedAt":1641896443998},"lib/css/themes/jquery-ui/humanity/images/ui-bg_glass_100_f5f0e5_1x400.png":{"acl":{"owner":"system.user.admin","ownerGroup":"system.group.administrator","permissions":1632},"stats":{"size":393},"mimeType":"image/png","binary":true,"modifiedAt":1641896444061},"lib/css/themes/jquery-ui/humanity/images/ui-bg_flat_75_aaaaaa_40x100.png":{"acl":{"owner":"system.user.admin","ownerGroup":"system.group.administrator","permissions":1632},"stats":{"size":251},"mimeType":"image/png","binary":true,"modifiedAt":1641896444127},"lib/css/themes/jquery-ui/hot-sneaks/theme.css":{"acl":{"owner":"system.user.admin","ownerGroup":"system.group.administrator","permissions":1632},"stats":{"size":17366},"mimeType":"text/css","binary":false,"modifiedAt":1641896444194},"lib/css/themes/jquery-ui/hot-sneaks/jquery-ui.min.css":{"acl":{"owner":"system.user.admin","ownerGroup":"system.group.administrator","permissions":1632},"stats":{"size":30118},"mimeType":"text/css","binary":false,"modifiedAt":1641896444255},"lib/css/themes/jquery-ui/hot-sneaks/jquery-ui.css":{"acl":{"owner":"system.user.admin","ownerGroup":"system.group.administrator","permissions":1632},"stats":{"size":35294},"mimeType":"text/css","binary":false,"modifiedAt":1641896444319},"lib/css/themes/jquery-ui/hot-sneaks/images/ui-icons_ffffff_256x240.png":{"acl":{"owner":"system.user.admin","ownerGroup":"system.group.administrator","permissions":1632},"stats":{"size":6468},"mimeType":"image/png","binary":true,"modifiedAt":1641896444382},"lib/css/themes/jquery-ui/hot-sneaks/images/ui-icons_ffeb33_256x240.png":{"acl":{"owner":"system.user.admin","ownerGroup":"system.group.administrator","permissions":1632},"stats":{"size":4599},"mimeType":"image/png","binary":true,"modifiedAt":1641896444892},"lib/css/themes/jquery-ui/hot-sneaks/images/ui-icons_e1e463_256x240.png":{"acl":{"owner":"system.user.admin","ownerGroup":"system.group.administrator","permissions":1632},"stats":{"size":4599},"mimeType":"image/png","binary":true,"modifiedAt":1641896445251},"lib/css/themes/jquery-ui/hot-sneaks/images/ui-icons_c02669_256x240.png":{"acl":{"owner":"system.user.admin","ownerGroup":"system.group.administrator","permissions":1632},"stats":{"size":4599},"mimeType":"image/png","binary":true,"modifiedAt":1641896445314},"lib/css/themes/jquery-ui/hot-sneaks/images/ui-icons_88a206_256x240.png":{"acl":{"owner":"system.user.admin","ownerGroup":"system.group.administrator","permissions":1632},"stats":{"size":4599},"mimeType":"image/png","binary":true,"modifiedAt":1641896445380},"lib/css/themes/jquery-ui/hot-sneaks/images/ui-icons_454545_256x240.png":{"acl":{"owner":"system.user.admin","ownerGroup":"system.group.administrator","permissions":1632},"stats":{"size":7071},"mimeType":"image/png","binary":true,"modifiedAt":1641896445442},"lib/css/themes/jquery-ui/hot-sneaks/images/ui-bg_white-lines_85_f7f7ba_40x100.png":{"acl":{"owner":"system.user.admin","ownerGroup":"system.group.administrator","permissions":1632},"stats":{"size":403},"mimeType":"image/png","binary":true,"modifiedAt":1641896445504},"lib/css/themes/jquery-ui/hot-sneaks/images/ui-bg_flat_75_ffffff_40x100.png":{"acl":{"owner":"system.user.admin","ownerGroup":"system.group.administrator","permissions":1632},"stats":{"size":247},"mimeType":"image/png","binary":true,"modifiedAt":1641896445568},"lib/css/themes/jquery-ui/hot-sneaks/images/ui-bg_flat_75_ba9217_40x100.png":{"acl":{"owner":"system.user.admin","ownerGroup":"system.group.administrator","permissions":1632},"stats":{"size":261},"mimeType":"image/png","binary":true,"modifiedAt":1641896445631},"lib/css/themes/jquery-ui/hot-sneaks/images/ui-bg_dots-small_35_35414f_2x2.png":{"acl":{"owner":"system.user.admin","ownerGroup":"system.group.administrator","permissions":1632},"stats":{"size":262},"mimeType":"image/png","binary":true,"modifiedAt":1641896445693},"lib/css/themes/jquery-ui/hot-sneaks/images/ui-bg_dots-medium_80_ffff38_4x4.png":{"acl":{"owner":"system.user.admin","ownerGroup":"system.group.administrator","permissions":1632},"stats":{"size":264},"mimeType":"image/png","binary":true,"modifiedAt":1641896445754},"lib/css/themes/jquery-ui/hot-sneaks/images/ui-bg_diagonals-small_75_ccd232_40x40.png":{"acl":{"owner":"system.user.admin","ownerGroup":"system.group.administrator","permissions":1632},"stats":{"size":372},"mimeType":"image/png","binary":true,"modifiedAt":1641896445816},"lib/css/themes/jquery-ui/hot-sneaks/images/ui-bg_diagonals-small_50_ff3853_40x40.png":{"acl":{"owner":"system.user.admin","ownerGroup":"system.group.administrator","permissions":1632},"stats":{"size":369},"mimeType":"image/png","binary":true,"modifiedAt":1641896445878},"lib/css/themes/jquery-ui/hot-sneaks/images/ui-bg_diagonals-small_50_93c3cd_40x40.png":{"acl":{"owner":"system.user.admin","ownerGroup":"system.group.administrator","permissions":1632},"stats":{"size":372},"mimeType":"image/png","binary":true,"modifiedAt":1641896445941},"lib/css/themes/jquery-ui/hot-sneaks/images/ui-bg_diagonals-small_40_db4865_40x40.png":{"acl":{"owner":"system.user.admin","ownerGroup":"system.group.administrator","permissions":1632},"stats":{"size":371},"mimeType":"image/png","binary":true,"modifiedAt":1641896446005},"lib/css/themes/jquery-ui/flick/theme.css":{"acl":{"owner":"system.user.admin","ownerGroup":"system.group.administrator","permissions":1632},"stats":{"size":17318},"mimeType":"text/css","binary":false,"modifiedAt":1641896446069},"lib/css/themes/jquery-ui/flick/jquery-ui.min.css":{"acl":{"owner":"system.user.admin","ownerGroup":"system.group.administrator","permissions":1632},"stats":{"size":30029},"mimeType":"text/css","binary":false,"modifiedAt":1641896446132},"lib/css/themes/jquery-ui/flick/jquery-ui.css":{"acl":{"owner":"system.user.admin","ownerGroup":"system.group.administrator","permissions":1632},"stats":{"size":35246},"mimeType":"text/css","binary":false,"modifiedAt":1641896446194},"lib/css/themes/jquery-ui/flick/images/ui-icons_ffffff_256x240.png":{"acl":{"owner":"system.user.admin","ownerGroup":"system.group.administrator","permissions":1632},"stats":{"size":6468},"mimeType":"image/png","binary":true,"modifiedAt":1641896446258},"lib/css/themes/jquery-ui/flick/images/ui-icons_ff0084_256x240.png":{"acl":{"owner":"system.user.admin","ownerGroup":"system.group.administrator","permissions":1632},"stats":{"size":4599},"mimeType":"image/png","binary":true,"modifiedAt":1641896446321},"lib/css/themes/jquery-ui/flick/images/ui-icons_666666_256x240.png":{"acl":{"owner":"system.user.admin","ownerGroup":"system.group.administrator","permissions":1632},"stats":{"size":7092},"mimeType":"image/png","binary":true,"modifiedAt":1641896446383},"lib/css/themes/jquery-ui/flick/images/ui-icons_454545_256x240.png":{"acl":{"owner":"system.user.admin","ownerGroup":"system.group.administrator","permissions":1632},"stats":{"size":7071},"mimeType":"image/png","binary":true,"modifiedAt":1641896446446},"lib/css/themes/jquery-ui/flick/images/ui-icons_0073ea_256x240.png":{"acl":{"owner":"system.user.admin","ownerGroup":"system.group.administrator","permissions":1632},"stats":{"size":4599},"mimeType":"image/png","binary":true,"modifiedAt":1641896446513},"lib/css/themes/jquery-ui/flick/images/ui-bg_highlight-soft_50_dddddd_1x100.png":{"acl":{"owner":"system.user.admin","ownerGroup":"system.group.administrator","permissions":1632},"stats":{"size":319},"mimeType":"image/png","binary":true,"modifiedAt":1641896446577},"lib/css/themes/jquery-ui/flick/images/ui-bg_highlight-soft_25_0073ea_1x100.png":{"acl":{"owner":"system.user.admin","ownerGroup":"system.group.administrator","permissions":1632},"stats":{"size":374},"mimeType":"image/png","binary":true,"modifiedAt":1641896446639},"lib/css/themes/jquery-ui/flick/images/ui-bg_highlight-soft_100_f6f6f6_1x100.png":{"acl":{"owner":"system.user.admin","ownerGroup":"system.group.administrator","permissions":1632},"stats":{"size":316},"mimeType":"image/png","binary":true,"modifiedAt":1641896446702},"lib/css/themes/jquery-ui/flick/images/ui-bg_glass_65_ffffff_1x400.png":{"acl":{"owner":"system.user.admin","ownerGroup":"system.group.administrator","permissions":1632},"stats":{"size":246},"mimeType":"image/png","binary":true,"modifiedAt":1641896446765},"lib/css/themes/jquery-ui/flick/images/ui-bg_flat_75_ffffff_40x100.png":{"acl":{"owner":"system.user.admin","ownerGroup":"system.group.administrator","permissions":1632},"stats":{"size":247},"mimeType":"image/png","binary":true,"modifiedAt":1641896446827},"lib/css/themes/jquery-ui/flick/images/ui-bg_flat_55_ffffff_40x100.png":{"acl":{"owner":"system.user.admin","ownerGroup":"system.group.administrator","permissions":1632},"stats":{"size":247},"mimeType":"image/png","binary":true,"modifiedAt":1641896446890},"lib/css/themes/jquery-ui/flick/images/ui-bg_flat_0_eeeeee_40x100.png":{"acl":{"owner":"system.user.admin","ownerGroup":"system.group.administrator","permissions":1632},"stats":{"size":259},"mimeType":"image/png","binary":true,"modifiedAt":1641896446955},"lib/css/themes/jquery-ui/flick/images/ui-bg_flat_0_aaaaaa_40x100.png":{"acl":{"owner":"system.user.admin","ownerGroup":"system.group.administrator","permissions":1632},"stats":{"size":251},"mimeType":"image/png","binary":true,"modifiedAt":1641896447018},"lib/css/themes/jquery-ui/excite-bike/theme.css":{"acl":{"owner":"system.user.admin","ownerGroup":"system.group.administrator","permissions":1632},"stats":{"size":17385},"mimeType":"text/css","binary":false,"modifiedAt":1641896447081},"lib/css/themes/jquery-ui/excite-bike/jquery-ui.min.css":{"acl":{"owner":"system.user.admin","ownerGroup":"system.group.administrator","permissions":1632},"stats":{"size":30111},"mimeType":"text/css","binary":false,"modifiedAt":1641896447144},"lib/css/themes/jquery-ui/excite-bike/jquery-ui.css":{"acl":{"owner":"system.user.admin","ownerGroup":"system.group.administrator","permissions":1632},"stats":{"size":35313},"mimeType":"text/css","binary":false,"modifiedAt":1641896447209},"lib/css/themes/jquery-ui/excite-bike/images/ui-icons_ffffff_256x240.png":{"acl":{"owner":"system.user.admin","ownerGroup":"system.group.administrator","permissions":1632},"stats":{"size":6468},"mimeType":"image/png","binary":true,"modifiedAt":1641896447271},"lib/css/themes/jquery-ui/excite-bike/images/ui-icons_fcdd4a_256x240.png":{"acl":{"owner":"system.user.admin","ownerGroup":"system.group.administrator","permissions":1632},"stats":{"size":4599},"mimeType":"image/png","binary":true,"modifiedAt":1641896447340},"lib/css/themes/jquery-ui/excite-bike/images/ui-icons_5fa5e3_256x240.png":{"acl":{"owner":"system.user.admin","ownerGroup":"system.group.administrator","permissions":1632},"stats":{"size":4599},"mimeType":"image/png","binary":true,"modifiedAt":1641896447403},"lib/css/themes/jquery-ui/excite-bike/images/ui-icons_0b54d5_256x240.png":{"acl":{"owner":"system.user.admin","ownerGroup":"system.group.administrator","permissions":1632},"stats":{"size":4599},"mimeType":"image/png","binary":true,"modifiedAt":1641896447464},"lib/css/themes/jquery-ui/excite-bike/images/ui-icons_0a82eb_256x240.png":{"acl":{"owner":"system.user.admin","ownerGroup":"system.group.administrator","permissions":1632},"stats":{"size":4599},"mimeType":"image/png","binary":true,"modifiedAt":1641896447526},"lib/css/themes/jquery-ui/excite-bike/images/ui-bg_inset-hard_100_eeeeee_1x100.png":{"acl":{"owner":"system.user.admin","ownerGroup":"system.group.administrator","permissions":1632},"stats":{"size":292},"mimeType":"image/png","binary":true,"modifiedAt":1641896447587},"lib/css/themes/jquery-ui/excite-bike/images/ui-bg_highlight-soft_100_f9f9f9_1x100.png":{"acl":{"owner":"system.user.admin","ownerGroup":"system.group.administrator","permissions":1632},"stats":{"size":316},"mimeType":"image/png","binary":true,"modifiedAt":1641896447647},"lib/css/themes/jquery-ui/excite-bike/images/ui-bg_flat_0_e6b900_40x100.png":{"acl":{"owner":"system.user.admin","ownerGroup":"system.group.administrator","permissions":1632},"stats":{"size":261},"mimeType":"image/png","binary":true,"modifiedAt":1641896447711},"lib/css/themes/jquery-ui/excite-bike/images/ui-bg_flat_0_e69700_40x100.png":{"acl":{"owner":"system.user.admin","ownerGroup":"system.group.administrator","permissions":1632},"stats":{"size":261},"mimeType":"image/png","binary":true,"modifiedAt":1641896447774},"lib/css/themes/jquery-ui/excite-bike/images/ui-bg_diagonals-thick_26_2293f7_40x40.png":{"acl":{"owner":"system.user.admin","ownerGroup":"system.group.administrator","permissions":1632},"stats":{"size":445},"mimeType":"image/png","binary":true,"modifiedAt":1641896447837},"lib/css/themes/jquery-ui/excite-bike/images/ui-bg_diagonals-thick_22_1484e6_40x40.png":{"acl":{"owner":"system.user.admin","ownerGroup":"system.group.administrator","permissions":1632},"stats":{"size":448},"mimeType":"image/png","binary":true,"modifiedAt":1641896447899},"lib/css/themes/jquery-ui/excite-bike/images/ui-bg_diagonals-thick_20_e69700_40x40.png":{"acl":{"owner":"system.user.admin","ownerGroup":"system.group.administrator","permissions":1632},"stats":{"size":456},"mimeType":"image/png","binary":true,"modifiedAt":1641896447993},"lib/css/themes/jquery-ui/excite-bike/images/ui-bg_diagonals-small_25_c5ddfc_40x40.png":{"acl":{"owner":"system.user.admin","ownerGroup":"system.group.administrator","permissions":1632},"stats":{"size":381},"mimeType":"image/png","binary":true,"modifiedAt":1641896448057},"lib/css/themes/jquery-ui/eggplant/theme.css":{"acl":{"owner":"system.user.admin","ownerGroup":"system.group.administrator","permissions":1632},"stats":{"size":17405},"mimeType":"text/css","binary":false,"modifiedAt":1641896448123},"lib/css/themes/jquery-ui/eggplant/jquery-ui.min.css":{"acl":{"owner":"system.user.admin","ownerGroup":"system.group.administrator","permissions":1632},"stats":{"size":30146},"mimeType":"text/css","binary":false,"modifiedAt":1641896448190},"lib/css/themes/jquery-ui/eggplant/jquery-ui.css":{"acl":{"owner":"system.user.admin","ownerGroup":"system.group.administrator","permissions":1632},"stats":{"size":35333},"mimeType":"text/css","binary":false,"modifiedAt":1641896448251},"lib/css/themes/jquery-ui/eggplant/images/ui-icons_ffffff_256x240.png":{"acl":{"owner":"system.user.admin","ownerGroup":"system.group.administrator","permissions":1632},"stats":{"size":6468},"mimeType":"image/png","binary":true,"modifiedAt":1641896448314},"lib/css/themes/jquery-ui/eggplant/images/ui-icons_ebccce_256x240.png":{"acl":{"owner":"system.user.admin","ownerGroup":"system.group.administrator","permissions":1632},"stats":{"size":4599},"mimeType":"image/png","binary":true,"modifiedAt":1641896448381},"lib/css/themes/jquery-ui/eggplant/images/ui-icons_a8a3ae_256x240.png":{"acl":{"owner":"system.user.admin","ownerGroup":"system.group.administrator","permissions":1632},"stats":{"size":4599},"mimeType":"image/png","binary":true,"modifiedAt":1641896448445},"lib/css/themes/jquery-ui/eggplant/images/ui-icons_8d78a5_256x240.png":{"acl":{"owner":"system.user.admin","ownerGroup":"system.group.administrator","permissions":1632},"stats":{"size":4599},"mimeType":"image/png","binary":true,"modifiedAt":1641896448507},"lib/css/themes/jquery-ui/eggplant/images/ui-icons_734d99_256x240.png":{"acl":{"owner":"system.user.admin","ownerGroup":"system.group.administrator","permissions":1632},"stats":{"size":4599},"mimeType":"image/png","binary":true,"modifiedAt":1641896448568},"lib/css/themes/jquery-ui/eggplant/images/ui-icons_454545_256x240.png":{"acl":{"owner":"system.user.admin","ownerGroup":"system.group.administrator","permissions":1632},"stats":{"size":7071},"mimeType":"image/png","binary":true,"modifiedAt":1641896448631},"lib/css/themes/jquery-ui/eggplant/images/ui-bg_highlight-soft_45_5f5964_1x100.png":{"acl":{"owner":"system.user.admin","ownerGroup":"system.group.administrator","permissions":1632},"stats":{"size":400},"mimeType":"image/png","binary":true,"modifiedAt":1641896448694},"lib/css/themes/jquery-ui/eggplant/images/ui-bg_highlight-soft_25_30273a_1x100.png":{"acl":{"owner":"system.user.admin","ownerGroup":"system.group.administrator","permissions":1632},"stats":{"size":408},"mimeType":"image/png","binary":true,"modifiedAt":1641896448758},"lib/css/themes/jquery-ui/eggplant/images/ui-bg_highlight-soft_100_eae6ea_1x100.png":{"acl":{"owner":"system.user.admin","ownerGroup":"system.group.administrator","permissions":1632},"stats":{"size":412},"mimeType":"image/png","binary":true,"modifiedAt":1641896448821},"lib/css/themes/jquery-ui/eggplant/images/ui-bg_highlight-soft_100_dcd9de_1x100.png":{"acl":{"owner":"system.user.admin","ownerGroup":"system.group.administrator","permissions":1632},"stats":{"size":381},"mimeType":"image/png","binary":true,"modifiedAt":1641896448882},"lib/css/themes/jquery-ui/eggplant/images/ui-bg_gloss-wave_30_3d3644_500x100.png":{"acl":{"owner":"system.user.admin","ownerGroup":"system.group.administrator","permissions":1632},"stats":{"size":5980},"mimeType":"image/png","binary":true,"modifiedAt":1641896448946},"lib/css/themes/jquery-ui/eggplant/images/ui-bg_flat_55_fafafa_40x100.png":{"acl":{"owner":"system.user.admin","ownerGroup":"system.group.administrator","permissions":1632},"stats":{"size":269},"mimeType":"image/png","binary":true,"modifiedAt":1641896449012},"lib/css/themes/jquery-ui/eggplant/images/ui-bg_flat_55_994d53_40x100.png":{"acl":{"owner":"system.user.admin","ownerGroup":"system.group.administrator","permissions":1632},"stats":{"size":261},"mimeType":"image/png","binary":true,"modifiedAt":1641896449074},"lib/css/themes/jquery-ui/eggplant/images/ui-bg_flat_0_eeeeee_40x100.png":{"acl":{"owner":"system.user.admin","ownerGroup":"system.group.administrator","permissions":1632},"stats":{"size":259},"mimeType":"image/png","binary":true,"modifiedAt":1641896449140},"lib/css/themes/jquery-ui/eggplant/images/ui-bg_flat_0_aaaaaa_40x100.png":{"acl":{"owner":"system.user.admin","ownerGroup":"system.group.administrator","permissions":1632},"stats":{"size":251},"mimeType":"image/png","binary":true,"modifiedAt":1641896449202},"lib/css/themes/jquery-ui/dot-luv/theme.css":{"acl":{"owner":"system.user.admin","ownerGroup":"system.group.administrator","permissions":1632},"stats":{"size":17288},"mimeType":"text/css","binary":false,"modifiedAt":1641896449265},"lib/css/themes/jquery-ui/dot-luv/jquery-ui.min.css":{"acl":{"owner":"system.user.admin","ownerGroup":"system.group.administrator","permissions":1632},"stats":{"size":30022},"mimeType":"text/css","binary":false,"modifiedAt":1641896449327},"lib/css/themes/jquery-ui/dot-luv/jquery-ui.css":{"acl":{"owner":"system.user.admin","ownerGroup":"system.group.administrator","permissions":1632},"stats":{"size":35216},"mimeType":"text/css","binary":false,"modifiedAt":1641896449390},"lib/css/themes/jquery-ui/dot-luv/images/ui-icons_ffffff_256x240.png":{"acl":{"owner":"system.user.admin","ownerGroup":"system.group.administrator","permissions":1632},"stats":{"size":6468},"mimeType":"image/png","binary":true,"modifiedAt":1641896449454},"lib/css/themes/jquery-ui/dot-luv/images/ui-icons_9ccdfc_256x240.png":{"acl":{"owner":"system.user.admin","ownerGroup":"system.group.administrator","permissions":1632},"stats":{"size":4599},"mimeType":"image/png","binary":true,"modifiedAt":1641896449517},"lib/css/themes/jquery-ui/dot-luv/images/ui-icons_98d2fb_256x240.png":{"acl":{"owner":"system.user.admin","ownerGroup":"system.group.administrator","permissions":1632},"stats":{"size":4599},"mimeType":"image/png","binary":true,"modifiedAt":1641896449580},"lib/css/themes/jquery-ui/dot-luv/images/ui-icons_00498f_256x240.png":{"acl":{"owner":"system.user.admin","ownerGroup":"system.group.administrator","permissions":1632},"stats":{"size":4599},"mimeType":"image/png","binary":true,"modifiedAt":1641896449642},"lib/css/themes/jquery-ui/dot-luv/images/ui-bg_gloss-wave_20_111111_500x100.png":{"acl":{"owner":"system.user.admin","ownerGroup":"system.group.administrator","permissions":1632},"stats":{"size":3808},"mimeType":"image/png","binary":true,"modifiedAt":1641896449705},"lib/css/themes/jquery-ui/dot-luv/images/ui-bg_flat_40_292929_40x100.png":{"acl":{"owner":"system.user.admin","ownerGroup":"system.group.administrator","permissions":1632},"stats":{"size":269},"mimeType":"image/png","binary":true,"modifiedAt":1641896449771},"lib/css/themes/jquery-ui/dot-luv/images/ui-bg_flat_0_aaaaaa_40x100.png":{"acl":{"owner":"system.user.admin","ownerGroup":"system.group.administrator","permissions":1632},"stats":{"size":251},"mimeType":"image/png","binary":true,"modifiedAt":1641896449835},"lib/css/themes/jquery-ui/dot-luv/images/ui-bg_dots-small_40_00498f_2x2.png":{"acl":{"owner":"system.user.admin","ownerGroup":"system.group.administrator","permissions":1632},"stats":{"size":263},"mimeType":"image/png","binary":true,"modifiedAt":1641896449898},"lib/css/themes/jquery-ui/dot-luv/images/ui-bg_dots-small_30_a32d00_2x2.png":{"acl":{"owner":"system.user.admin","ownerGroup":"system.group.administrator","permissions":1632},"stats":{"size":257},"mimeType":"image/png","binary":true,"modifiedAt":1641896449971},"lib/css/themes/jquery-ui/dot-luv/images/ui-bg_dots-small_20_333333_2x2.png":{"acl":{"owner":"system.user.admin","ownerGroup":"system.group.administrator","permissions":1632},"stats":{"size":245},"mimeType":"image/png","binary":true,"modifiedAt":1641896450034},"lib/css/themes/jquery-ui/dot-luv/images/ui-bg_dots-medium_30_0b58a2_4x4.png":{"acl":{"owner":"system.user.admin","ownerGroup":"system.group.administrator","permissions":1632},"stats":{"size":276},"mimeType":"image/png","binary":true,"modifiedAt":1641896450091},"lib/css/themes/jquery-ui/dot-luv/images/ui-bg_diagonals-thick_15_0b3e6f_40x40.png":{"acl":{"owner":"system.user.admin","ownerGroup":"system.group.administrator","permissions":1632},"stats":{"size":463},"mimeType":"image/png","binary":true,"modifiedAt":1641896450148},"lib/css/themes/jquery-ui/default/jquery-ui.theme.min.css":{"acl":{"owner":"system.user.admin","ownerGroup":"system.group.administrator","permissions":1632},"stats":{"size":13327},"mimeType":"text/css","binary":false,"modifiedAt":1641896450205},"lib/css/themes/jquery-ui/default/jquery-ui.structure.min.css":{"acl":{"owner":"system.user.admin","ownerGroup":"system.group.administrator","permissions":1632},"stats":{"size":14764},"mimeType":"text/css","binary":false,"modifiedAt":1641896450264},"lib/css/themes/jquery-ui/default/jquery-ui.min.css":{"acl":{"owner":"system.user.admin","ownerGroup":"system.group.administrator","permissions":1632},"stats":{"size":29636},"mimeType":"text/css","binary":false,"modifiedAt":1641896450320},"lib/css/themes/jquery-ui/default/images/ui-icons_ffffff_256x240.png":{"acl":{"owner":"system.user.admin","ownerGroup":"system.group.administrator","permissions":1632},"stats":{"size":6299},"mimeType":"image/png","binary":true,"modifiedAt":1641896450437},"lib/css/themes/jquery-ui/default/images/ui-icons_d8d8d8_256x240.png":{"acl":{"owner":"system.user.admin","ownerGroup":"system.group.administrator","permissions":1632},"stats":{"size":6956},"mimeType":"image/png","binary":true,"modifiedAt":1641896450494},"lib/css/themes/jquery-ui/default/images/ui-icons_6F6F6F_256x240.png":{"acl":{"owner":"system.user.admin","ownerGroup":"system.group.administrator","permissions":1632},"stats":{"size":6997},"mimeType":"image/png","binary":true,"modifiedAt":1641896450550},"lib/css/themes/jquery-ui/default/images/ui-icons_5fa5e3_256x240.png":{"acl":{"owner":"system.user.admin","ownerGroup":"system.group.administrator","permissions":1632},"stats":{"size":4549},"mimeType":"image/png","binary":true,"modifiedAt":1641896450607},"lib/css/themes/jquery-ui/default/images/ui-icons_2293f7_256x240.png":{"acl":{"owner":"system.user.admin","ownerGroup":"system.group.administrator","permissions":1632},"stats":{"size":4549},"mimeType":"image/png","binary":true,"modifiedAt":1641896450664},"lib/css/themes/jquery-ui/default/images/ui-icons_0a82eb_256x240.png":{"acl":{"owner":"system.user.admin","ownerGroup":"system.group.administrator","permissions":1632},"stats":{"size":4549},"mimeType":"image/png","binary":true,"modifiedAt":1641896450721},"lib/css/themes/jquery-ui/default/images/ui-bg_highlight-hard_50_c5ddfc_1x100.png":{"acl":{"owner":"system.user.admin","ownerGroup":"system.group.administrator","permissions":1632},"stats":{"size":315},"mimeType":"image/png","binary":true,"modifiedAt":1641896450785},"lib/css/themes/jquery-ui/default/images/ui-bg_glow-ball_100_efefef_600x600.png":{"acl":{"owner":"system.user.admin","ownerGroup":"system.group.administrator","permissions":1632},"stats":{"size":34054},"mimeType":"image/png","binary":true,"modifiedAt":1641896450849},"lib/css/themes/jquery-ui/dark-hive/theme.css":{"acl":{"owner":"system.user.admin","ownerGroup":"system.group.administrator","permissions":1632},"stats":{"size":17357},"mimeType":"text/css","binary":false,"modifiedAt":1641896450911},"lib/css/themes/jquery-ui/dark-hive/jquery-ui.min.css":{"acl":{"owner":"system.user.admin","ownerGroup":"system.group.administrator","permissions":1632},"stats":{"size":30073},"mimeType":"text/css","binary":false,"modifiedAt":1641896450974},"lib/css/themes/jquery-ui/dark-hive/jquery-ui.css":{"acl":{"owner":"system.user.admin","ownerGroup":"system.group.administrator","permissions":1632},"stats":{"size":35285},"mimeType":"text/css","binary":false,"modifiedAt":1641896451040},"lib/css/themes/jquery-ui/dark-hive/images/ui-icons_ffffff_256x240.png":{"acl":{"owner":"system.user.admin","ownerGroup":"system.group.administrator","permissions":1632},"stats":{"size":6468},"mimeType":"image/png","binary":true,"modifiedAt":1641896451105},"lib/css/themes/jquery-ui/dark-hive/images/ui-icons_cccccc_256x240.png":{"acl":{"owner":"system.user.admin","ownerGroup":"system.group.administrator","permissions":1632},"stats":{"size":7015},"mimeType":"image/png","binary":true,"modifiedAt":1641896451170},"lib/css/themes/jquery-ui/dark-hive/images/ui-icons_a83300_256x240.png":{"acl":{"owner":"system.user.admin","ownerGroup":"system.group.administrator","permissions":1632},"stats":{"size":4599},"mimeType":"image/png","binary":true,"modifiedAt":1641896451232},"lib/css/themes/jquery-ui/dark-hive/images/ui-icons_4b8e0b_256x240.png":{"acl":{"owner":"system.user.admin","ownerGroup":"system.group.administrator","permissions":1632},"stats":{"size":4599},"mimeType":"image/png","binary":true,"modifiedAt":1641896451295},"lib/css/themes/jquery-ui/dark-hive/images/ui-icons_222222_256x240.png":{"acl":{"owner":"system.user.admin","ownerGroup":"system.group.administrator","permissions":1632},"stats":{"size":7006},"mimeType":"image/png","binary":true,"modifiedAt":1641896451358},"lib/css/themes/jquery-ui/dark-hive/images/ui-bg_loop_25_000000_21x21.png":{"acl":{"owner":"system.user.admin","ownerGroup":"system.group.administrator","permissions":1632},"stats":{"size":324},"mimeType":"image/png","binary":true,"modifiedAt":1641896451422},"lib/css/themes/jquery-ui/dark-hive/images/ui-bg_highlight-soft_80_eeeeee_1x100.png":{"acl":{"owner":"system.user.admin","ownerGroup":"system.group.administrator","permissions":1632},"stats":{"size":315},"mimeType":"image/png","binary":true,"modifiedAt":1641896451486},"lib/css/themes/jquery-ui/dark-hive/images/ui-bg_highlight-soft_44_444444_1x100.png":{"acl":{"owner":"system.user.admin","ownerGroup":"system.group.administrator","permissions":1632},"stats":{"size":316},"mimeType":"image/png","binary":true,"modifiedAt":1641896451557},"lib/css/themes/jquery-ui/dark-hive/images/ui-bg_highlight-soft_35_222222_1x100.png":{"acl":{"owner":"system.user.admin","ownerGroup":"system.group.administrator","permissions":1632},"stats":{"size":316},"mimeType":"image/png","binary":true,"modifiedAt":1641896451620},"lib/css/themes/jquery-ui/dark-hive/images/ui-bg_highlight-soft_33_003147_1x100.png":{"acl":{"owner":"system.user.admin","ownerGroup":"system.group.administrator","permissions":1632},"stats":{"size":391},"mimeType":"image/png","binary":true,"modifiedAt":1641896451682},"lib/css/themes/jquery-ui/dark-hive/images/ui-bg_highlight-hard_20_0972a5_1x100.png":{"acl":{"owner":"system.user.admin","ownerGroup":"system.group.administrator","permissions":1632},"stats":{"size":362},"mimeType":"image/png","binary":true,"modifiedAt":1641896451745},"lib/css/themes/jquery-ui/dark-hive/images/ui-bg_glass_40_ffc73d_1x400.png":{"acl":{"owner":"system.user.admin","ownerGroup":"system.group.administrator","permissions":1632},"stats":{"size":355},"mimeType":"image/png","binary":true,"modifiedAt":1641896451809},"lib/css/themes/jquery-ui/dark-hive/images/ui-bg_flat_50_5c5c5c_40x100.png":{"acl":{"owner":"system.user.admin","ownerGroup":"system.group.administrator","permissions":1632},"stats":{"size":269},"mimeType":"image/png","binary":true,"modifiedAt":1641896451873},"lib/css/themes/jquery-ui/dark-hive/images/ui-bg_flat_30_cccccc_40x100.png":{"acl":{"owner":"system.user.admin","ownerGroup":"system.group.administrator","permissions":1632},"stats":{"size":259},"mimeType":"image/png","binary":true,"modifiedAt":1641896451936},"lib/css/themes/jquery-ui/custom-light/jquery-ui.theme.min.css":{"acl":{"owner":"system.user.admin","ownerGroup":"system.group.administrator","permissions":1632},"stats":{"size":13599},"mimeType":"text/css","binary":false,"modifiedAt":1641896451998},"lib/css/themes/jquery-ui/custom-light/jquery-ui.structure.min.css":{"acl":{"owner":"system.user.admin","ownerGroup":"system.group.administrator","permissions":1632},"stats":{"size":14764},"mimeType":"text/css","binary":false,"modifiedAt":1641896452063},"lib/css/themes/jquery-ui/custom-light/jquery-ui.min.css":{"acl":{"owner":"system.user.admin","ownerGroup":"system.group.administrator","permissions":1632},"stats":{"size":29919},"mimeType":"text/css","binary":false,"modifiedAt":1641896452126},"lib/css/themes/jquery-ui/custom-light/images/ui-icons_cd0a0a_256x240.png":{"acl":{"owner":"system.user.admin","ownerGroup":"system.group.administrator","permissions":1632},"stats":{"size":4549},"mimeType":"image/png","binary":true,"modifiedAt":1641896452194},"lib/css/themes/jquery-ui/custom-light/images/ui-icons_888888_256x240.png":{"acl":{"owner":"system.user.admin","ownerGroup":"system.group.administrator","permissions":1632},"stats":{"size":6999},"mimeType":"image/png","binary":true,"modifiedAt":1641896452256},"lib/css/themes/jquery-ui/custom-light/images/ui-icons_454545_256x240.png":{"acl":{"owner":"system.user.admin","ownerGroup":"system.group.administrator","permissions":1632},"stats":{"size":6992},"mimeType":"image/png","binary":true,"modifiedAt":1641896452318},"lib/css/themes/jquery-ui/custom-light/images/ui-icons_2e83ff_256x240.png":{"acl":{"owner":"system.user.admin","ownerGroup":"system.group.administrator","permissions":1632},"stats":{"size":4549},"mimeType":"image/png","binary":true,"modifiedAt":1641896452381},"lib/css/themes/jquery-ui/custom-light/images/ui-icons_222222_256x240.png":{"acl":{"owner":"system.user.admin","ownerGroup":"system.group.administrator","permissions":1632},"stats":{"size":6922},"mimeType":"image/png","binary":true,"modifiedAt":1641896452444},"lib/css/themes/jquery-ui/custom-light/images/ui-bg_highlight-soft_75_cccccc_1x100.png":{"acl":{"owner":"system.user.admin","ownerGroup":"system.group.administrator","permissions":1632},"stats":{"size":280},"mimeType":"image/png","binary":true,"modifiedAt":1641896452509},"lib/css/themes/jquery-ui/custom-light/images/ui-bg_glass_95_fef1ec_1x400.png":{"acl":{"owner":"system.user.admin","ownerGroup":"system.group.administrator","permissions":1632},"stats":{"size":332},"mimeType":"image/png","binary":true,"modifiedAt":1641896452573},"lib/css/themes/jquery-ui/custom-light/images/ui-bg_glass_75_e6e6e6_1x400.png":{"acl":{"owner":"system.user.admin","ownerGroup":"system.group.administrator","permissions":1632},"stats":{"size":262},"mimeType":"image/png","binary":true,"modifiedAt":1641896452636},"lib/css/themes/jquery-ui/custom-light/images/ui-bg_glass_75_dadada_1x400.png":{"acl":{"owner":"system.user.admin","ownerGroup":"system.group.administrator","permissions":1632},"stats":{"size":262},"mimeType":"image/png","binary":true,"modifiedAt":1641896452699},"lib/css/themes/jquery-ui/custom-light/images/ui-bg_glass_65_ffffff_1x400.png":{"acl":{"owner":"system.user.admin","ownerGroup":"system.group.administrator","permissions":1632},"stats":{"size":207},"mimeType":"image/png","binary":true,"modifiedAt":1641896452763},"lib/css/themes/jquery-ui/custom-light/images/ui-bg_glass_55_fbf9ee_1x400.png":{"acl":{"owner":"system.user.admin","ownerGroup":"system.group.administrator","permissions":1632},"stats":{"size":335},"mimeType":"image/png","binary":true,"modifiedAt":1641896452833},"lib/css/themes/jquery-ui/custom-dark/jquery-ui.theme.min.css":{"acl":{"owner":"system.user.admin","ownerGroup":"system.group.administrator","permissions":1632},"stats":{"size":13527},"mimeType":"text/css","binary":false,"modifiedAt":1641896452897},"lib/css/themes/jquery-ui/custom-dark/jquery-ui.structure.min.css":{"acl":{"owner":"system.user.admin","ownerGroup":"system.group.administrator","permissions":1632},"stats":{"size":14764},"mimeType":"text/css","binary":false,"modifiedAt":1641896452960},"lib/css/themes/jquery-ui/custom-dark/jquery-ui.min.css":{"acl":{"owner":"system.user.admin","ownerGroup":"system.group.administrator","permissions":1632},"stats":{"size":29864},"mimeType":"text/css","binary":false,"modifiedAt":1641896453025},"lib/css/themes/jquery-ui/custom-dark/images/ui-icons_ffffff_256x240.png":{"acl":{"owner":"system.user.admin","ownerGroup":"system.group.administrator","permissions":1632},"stats":{"size":6299},"mimeType":"image/png","binary":true,"modifiedAt":1641896453092},"lib/css/themes/jquery-ui/custom-dark/images/ui-icons_cccccc_256x240.png":{"acl":{"owner":"system.user.admin","ownerGroup":"system.group.administrator","permissions":1632},"stats":{"size":6975},"mimeType":"image/png","binary":true,"modifiedAt":1641896453166},"lib/css/themes/jquery-ui/custom-dark/images/ui-icons_a83300_256x240.png":{"acl":{"owner":"system.user.admin","ownerGroup":"system.group.administrator","permissions":1632},"stats":{"size":4549},"mimeType":"image/png","binary":true,"modifiedAt":1641896453230},"lib/css/themes/jquery-ui/custom-dark/images/ui-icons_4b8e0b_256x240.png":{"acl":{"owner":"system.user.admin","ownerGroup":"system.group.administrator","permissions":1632},"stats":{"size":4549},"mimeType":"image/png","binary":true,"modifiedAt":1641896453293},"lib/css/themes/jquery-ui/custom-dark/images/ui-icons_222222_256x240.png":{"acl":{"owner":"system.user.admin","ownerGroup":"system.group.administrator","permissions":1632},"stats":{"size":6922},"mimeType":"image/png","binary":true,"modifiedAt":1641896453355},"lib/css/themes/jquery-ui/custom-dark/images/ui-bg_highlight-soft_80_eeeeee_1x100.png":{"acl":{"owner":"system.user.admin","ownerGroup":"system.group.administrator","permissions":1632},"stats":{"size":276},"mimeType":"image/png","binary":true,"modifiedAt":1641896453422},"lib/css/themes/jquery-ui/custom-dark/images/ui-bg_highlight-soft_40_62bfe1_1x100.png":{"acl":{"owner":"system.user.admin","ownerGroup":"system.group.administrator","permissions":1632},"stats":{"size":355},"mimeType":"image/png","binary":true,"modifiedAt":1641896453494},"lib/css/themes/jquery-ui/custom-dark/images/ui-bg_highlight-soft_25_333333_1x100.png":{"acl":{"owner":"system.user.admin","ownerGroup":"system.group.administrator","permissions":1632},"stats":{"size":278},"mimeType":"image/png","binary":true,"modifiedAt":1641896453554},"lib/css/themes/jquery-ui/custom-dark/images/ui-bg_glass_40_ffc73d_1x400.png":{"acl":{"owner":"system.user.admin","ownerGroup":"system.group.administrator","permissions":1632},"stats":{"size":316},"mimeType":"image/png","binary":true,"modifiedAt":1641896453623},"lib/css/themes/jquery-ui/custom-dark/images/ui-bg_glass_20_555555_1x400.png":{"acl":{"owner":"system.user.admin","ownerGroup":"system.group.administrator","permissions":1632},"stats":{"size":260},"mimeType":"image/png","binary":true,"modifiedAt":1641896453688},"lib/css/themes/jquery-ui/cupertino/theme.css":{"acl":{"owner":"system.user.admin","ownerGroup":"system.group.administrator","permissions":1632},"stats":{"size":17420},"mimeType":"text/css","binary":false,"modifiedAt":1641896453754},"lib/css/themes/jquery-ui/cupertino/jquery-ui.min.css":{"acl":{"owner":"system.user.admin","ownerGroup":"system.group.administrator","permissions":1632},"stats":{"size":30172},"mimeType":"text/css","binary":false,"modifiedAt":1641896453820},"lib/css/themes/jquery-ui/cupertino/jquery-ui.css":{"acl":{"owner":"system.user.admin","ownerGroup":"system.group.administrator","permissions":1632},"stats":{"size":35348},"mimeType":"text/css","binary":false,"modifiedAt":1641896453884},"lib/css/themes/jquery-ui/cupertino/images/ui-icons_ffffff_256x240.png":{"acl":{"owner":"system.user.admin","ownerGroup":"system.group.administrator","permissions":1632},"stats":{"size":6468},"mimeType":"image/png","binary":true,"modifiedAt":1641896453948},"lib/css/themes/jquery-ui/cupertino/images/ui-icons_72a7cf_256x240.png":{"acl":{"owner":"system.user.admin","ownerGroup":"system.group.administrator","permissions":1632},"stats":{"size":4599},"mimeType":"image/png","binary":true,"modifiedAt":1641896454013},"lib/css/themes/jquery-ui/cupertino/images/ui-icons_3d80b3_256x240.png":{"acl":{"owner":"system.user.admin","ownerGroup":"system.group.administrator","permissions":1632},"stats":{"size":4599},"mimeType":"image/png","binary":true,"modifiedAt":1641896454079},"lib/css/themes/jquery-ui/cupertino/images/ui-icons_2e83ff_256x240.png":{"acl":{"owner":"system.user.admin","ownerGroup":"system.group.administrator","permissions":1632},"stats":{"size":4599},"mimeType":"image/png","binary":true,"modifiedAt":1641896454148},"lib/css/themes/jquery-ui/cupertino/images/ui-icons_2694e8_256x240.png":{"acl":{"owner":"system.user.admin","ownerGroup":"system.group.administrator","permissions":1632},"stats":{"size":4599},"mimeType":"image/png","binary":true,"modifiedAt":1641896454214},"lib/css/themes/jquery-ui/cupertino/images/ui-bg_highlight-soft_25_ffef8f_1x100.png":{"acl":{"owner":"system.user.admin","ownerGroup":"system.group.administrator","permissions":1632},"stats":{"size":348},"mimeType":"image/png","binary":true,"modifiedAt":1641896454276},"lib/css/themes/jquery-ui/cupertino/images/ui-bg_highlight-soft_100_deedf7_1x100.png":{"acl":{"owner":"system.user.admin","ownerGroup":"system.group.administrator","permissions":1632},"stats":{"size":426},"mimeType":"image/png","binary":true,"modifiedAt":1641896454339},"lib/css/themes/jquery-ui/cupertino/images/ui-bg_highlight-hard_70_000000_1x100.png":{"acl":{"owner":"system.user.admin","ownerGroup":"system.group.administrator","permissions":1632},"stats":{"size":288},"mimeType":"image/png","binary":true,"modifiedAt":1641896454406},"lib/css/themes/jquery-ui/cupertino/images/ui-bg_highlight-hard_100_f2f5f7_1x100.png":{"acl":{"owner":"system.user.admin","ownerGroup":"system.group.administrator","permissions":1632},"stats":{"size":371},"mimeType":"image/png","binary":true,"modifiedAt":1641896454499},"lib/css/themes/jquery-ui/cupertino/images/ui-bg_glass_80_d7ebf9_1x400.png":{"acl":{"owner":"system.user.admin","ownerGroup":"system.group.administrator","permissions":1632},"stats":{"size":385},"mimeType":"image/png","binary":true,"modifiedAt":1641896454561},"lib/css/themes/jquery-ui/cupertino/images/ui-bg_glass_50_3baae3_1x400.png":{"acl":{"owner":"system.user.admin","ownerGroup":"system.group.administrator","permissions":1632},"stats":{"size":375},"mimeType":"image/png","binary":true,"modifiedAt":1641896454622},"lib/css/themes/jquery-ui/cupertino/images/ui-bg_glass_100_e4f1fb_1x400.png":{"acl":{"owner":"system.user.admin","ownerGroup":"system.group.administrator","permissions":1632},"stats":{"size":389},"mimeType":"image/png","binary":true,"modifiedAt":1641896454683},"lib/css/themes/jquery-ui/cupertino/images/ui-bg_flat_15_cd0a0a_40x100.png":{"acl":{"owner":"system.user.admin","ownerGroup":"system.group.administrator","permissions":1632},"stats":{"size":261},"mimeType":"image/png","binary":true,"modifiedAt":1641896454748},"lib/css/themes/jquery-ui/cupertino/images/ui-bg_diagonals-thick_90_eeeeee_40x40.png":{"acl":{"owner":"system.user.admin","ownerGroup":"system.group.administrator","permissions":1632},"stats":{"size":351},"mimeType":"image/png","binary":true,"modifiedAt":1641896454815},"lib/css/themes/jquery-ui/blitzer/theme.css":{"acl":{"owner":"system.user.admin","ownerGroup":"system.group.administrator","permissions":1632},"stats":{"size":17316},"mimeType":"text/css","binary":false,"modifiedAt":1641896454879},"lib/css/themes/jquery-ui/blitzer/jquery-ui.min.css":{"acl":{"owner":"system.user.admin","ownerGroup":"system.group.administrator","permissions":1632},"stats":{"size":30044},"mimeType":"text/css","binary":false,"modifiedAt":1641896454943},"lib/css/themes/jquery-ui/blitzer/jquery-ui.css":{"acl":{"owner":"system.user.admin","ownerGroup":"system.group.administrator","permissions":1632},"stats":{"size":35244},"mimeType":"text/css","binary":false,"modifiedAt":1641896455009},"lib/css/themes/jquery-ui/blitzer/images/ui-icons_ffffff_256x240.png":{"acl":{"owner":"system.user.admin","ownerGroup":"system.group.administrator","permissions":1632},"stats":{"size":6468},"mimeType":"image/png","binary":true,"modifiedAt":1641896455070},"lib/css/themes/jquery-ui/blitzer/images/ui-icons_cc0000_256x240.png":{"acl":{"owner":"system.user.admin","ownerGroup":"system.group.administrator","permissions":1632},"stats":{"size":4599},"mimeType":"image/png","binary":true,"modifiedAt":1641896455134},"lib/css/themes/jquery-ui/blitzer/images/ui-icons_004276_256x240.png":{"acl":{"owner":"system.user.admin","ownerGroup":"system.group.administrator","permissions":1632},"stats":{"size":4599},"mimeType":"image/png","binary":true,"modifiedAt":1641896455199},"lib/css/themes/jquery-ui/blitzer/images/ui-bg_highlight-soft_15_cc0000_1x100.png":{"acl":{"owner":"system.user.admin","ownerGroup":"system.group.administrator","permissions":1632},"stats":{"size":366},"mimeType":"image/png","binary":true,"modifiedAt":1641896455263},"lib/css/themes/jquery-ui/blitzer/images/ui-bg_highlight-hard_100_f6f6f6_1x100.png":{"acl":{"owner":"system.user.admin","ownerGroup":"system.group.administrator","permissions":1632},"stats":{"size":290},"mimeType":"image/png","binary":true,"modifiedAt":1641896455326},"lib/css/themes/jquery-ui/blitzer/images/ui-bg_highlight-hard_100_eeeeee_1x100.png":{"acl":{"owner":"system.user.admin","ownerGroup":"system.group.administrator","permissions":1632},"stats":{"size":291},"mimeType":"image/png","binary":true,"modifiedAt":1641896455389},"lib/css/themes/jquery-ui/blitzer/images/ui-bg_glass_55_fbf8ee_1x400.png":{"acl":{"owner":"system.user.admin","ownerGroup":"system.group.administrator","permissions":1632},"stats":{"size":379},"mimeType":"image/png","binary":true,"modifiedAt":1641896455455},"lib/css/themes/jquery-ui/blitzer/images/ui-bg_flat_75_ffffff_40x100.png":{"acl":{"owner":"system.user.admin","ownerGroup":"system.group.administrator","permissions":1632},"stats":{"size":247},"mimeType":"image/png","binary":true,"modifiedAt":1641896455517},"lib/css/themes/jquery-ui/blitzer/images/ui-bg_flat_65_ffffff_40x100.png":{"acl":{"owner":"system.user.admin","ownerGroup":"system.group.administrator","permissions":1632},"stats":{"size":247},"mimeType":"image/png","binary":true,"modifiedAt":1641896455579},"lib/css/themes/jquery-ui/blitzer/images/ui-bg_flat_0_333333_40x100.png":{"acl":{"owner":"system.user.admin","ownerGroup":"system.group.administrator","permissions":1632},"stats":{"size":259},"mimeType":"image/png","binary":true,"modifiedAt":1641896455642},"lib/css/themes/jquery-ui/blitzer/images/ui-bg_dots-small_65_a6a6a6_2x2.png":{"acl":{"owner":"system.user.admin","ownerGroup":"system.group.administrator","permissions":1632},"stats":{"size":246},"mimeType":"image/png","binary":true,"modifiedAt":1641896455705},"lib/css/themes/jquery-ui/blitzer/images/ui-bg_diagonals-thick_75_f3d8d8_40x40.png":{"acl":{"owner":"system.user.admin","ownerGroup":"system.group.administrator","permissions":1632},"stats":{"size":452},"mimeType":"image/png","binary":true,"modifiedAt":1641896455770},"lib/css/themes/jquery-ui/black-tie/theme.css":{"acl":{"owner":"system.user.admin","ownerGroup":"system.group.administrator","permissions":1632},"stats":{"size":17370},"mimeType":"text/css","binary":false,"modifiedAt":1641896455835},"lib/css/themes/jquery-ui/black-tie/jquery-ui.min.css":{"acl":{"owner":"system.user.admin","ownerGroup":"system.group.administrator","permissions":1632},"stats":{"size":30092},"mimeType":"text/css","binary":false,"modifiedAt":1641896455898},"lib/css/themes/jquery-ui/black-tie/jquery-ui.css":{"acl":{"owner":"system.user.admin","ownerGroup":"system.group.administrator","permissions":1632},"stats":{"size":35298},"mimeType":"text/css","binary":false,"modifiedAt":1641896455963},"lib/css/themes/jquery-ui/black-tie/images/ui-icons_ffffff_256x240.png":{"acl":{"owner":"system.user.admin","ownerGroup":"system.group.administrator","permissions":1632},"stats":{"size":6468},"mimeType":"image/png","binary":true,"modifiedAt":1641896456028},"lib/css/themes/jquery-ui/black-tie/images/ui-icons_ffcf29_256x240.png":{"acl":{"owner":"system.user.admin","ownerGroup":"system.group.administrator","permissions":1632},"stats":{"size":4599},"mimeType":"image/png","binary":true,"modifiedAt":1641896456094},"lib/css/themes/jquery-ui/black-tie/images/ui-icons_ededed_256x240.png":{"acl":{"owner":"system.user.admin","ownerGroup":"system.group.administrator","permissions":1632},"stats":{"size":6992},"mimeType":"image/png","binary":true,"modifiedAt":1641896456157},"lib/css/themes/jquery-ui/black-tie/images/ui-icons_bbbbbb_256x240.png":{"acl":{"owner":"system.user.admin","ownerGroup":"system.group.administrator","permissions":1632},"stats":{"size":7073},"mimeType":"image/png","binary":true,"modifiedAt":1641896456224},"lib/css/themes/jquery-ui/black-tie/images/ui-icons_4ca300_256x240.png":{"acl":{"owner":"system.user.admin","ownerGroup":"system.group.administrator","permissions":1632},"stats":{"size":4599},"mimeType":"image/png","binary":true,"modifiedAt":1641896456289},"lib/css/themes/jquery-ui/black-tie/images/ui-icons_222222_256x240.png":{"acl":{"owner":"system.user.admin","ownerGroup":"system.group.administrator","permissions":1632},"stats":{"size":7006},"mimeType":"image/png","binary":true,"modifiedAt":1641896456353},"lib/css/themes/jquery-ui/black-tie/images/ui-bg_inset-hard_55_ffeb80_1x100.png":{"acl":{"owner":"system.user.admin","ownerGroup":"system.group.administrator","permissions":1632},"stats":{"size":348},"mimeType":"image/png","binary":true,"modifiedAt":1641896456415},"lib/css/themes/jquery-ui/black-tie/images/ui-bg_inset-hard_45_cd0a0a_1x100.png":{"acl":{"owner":"system.user.admin","ownerGroup":"system.group.administrator","permissions":1632},"stats":{"size":363},"mimeType":"image/png","binary":true,"modifiedAt":1641896456481},"lib/css/themes/jquery-ui/black-tie/images/ui-bg_highlight-soft_50_aaaaaa_1x100.png":{"acl":{"owner":"system.user.admin","ownerGroup":"system.group.administrator","permissions":1632},"stats":{"size":319},"mimeType":"image/png","binary":true,"modifiedAt":1641896456550},"lib/css/themes/jquery-ui/black-tie/images/ui-bg_highlight-hard_40_aaaaaa_1x100.png":{"acl":{"owner":"system.user.admin","ownerGroup":"system.group.administrator","permissions":1632},"stats":{"size":291},"mimeType":"image/png","binary":true,"modifiedAt":1641896456613},"lib/css/themes/jquery-ui/black-tie/images/ui-bg_highlight-hard_100_f9f9f9_1x100.png":{"acl":{"owner":"system.user.admin","ownerGroup":"system.group.administrator","permissions":1632},"stats":{"size":291},"mimeType":"image/png","binary":true,"modifiedAt":1641896456677},"lib/css/themes/jquery-ui/black-tie/images/ui-bg_glass_55_1c1c1c_1x400.png":{"acl":{"owner":"system.user.admin","ownerGroup":"system.group.administrator","permissions":1632},"stats":{"size":299},"mimeType":"image/png","binary":true,"modifiedAt":1641896456743},"lib/css/themes/jquery-ui/black-tie/images/ui-bg_glass_40_111111_1x400.png":{"acl":{"owner":"system.user.admin","ownerGroup":"system.group.administrator","permissions":1632},"stats":{"size":299},"mimeType":"image/png","binary":true,"modifiedAt":1641896456812},"lib/css/themes/jquery-ui/black-tie/images/ui-bg_flat_65_ffffff_40x100.png":{"acl":{"owner":"system.user.admin","ownerGroup":"system.group.administrator","permissions":1632},"stats":{"size":247},"mimeType":"image/png","binary":true,"modifiedAt":1641896456879},"lib/css/themes/jquery-ui/black-tie/images/ui-bg_diagonals-thick_8_333333_40x40.png":{"acl":{"owner":"system.user.admin","ownerGroup":"system.group.administrator","permissions":1632},"stats":{"size":351},"mimeType":"image/png","binary":true,"modifiedAt":1641896456944},"lib/css/style.css":{"acl":{"owner":"system.user.admin","ownerGroup":"system.group.administrator","permissions":1632},"stats":{"size":14464},"mimeType":"text/css","binary":false,"modifiedAt":1641896457009},"lib/css/materialize.css":{"acl":{"owner":"system.user.admin","ownerGroup":"system.group.administrator","permissions":1632},"stats":{"size":130844},"mimeType":"text/css","binary":false,"modifiedAt":1641896457119},"lib/css/jqGrid/ui.jqgrid-4.5.4.css":{"acl":{"owner":"system.user.admin","ownerGroup":"system.group.administrator","permissions":1632},"stats":{"size":12804},"mimeType":"text/css","binary":false,"modifiedAt":1641896457196},"lib/css/jqGrid/ellipsis-xbl.xml":{"acl":{"owner":"system.user.admin","ownerGroup":"system.group.administrator","permissions":1632},"stats":{"size":493},"mimeType":"text/xml","binary":false,"modifiedAt":1641896457267},"lib/css/iob/selectID.css.map":{"acl":{"owner":"system.user.admin","ownerGroup":"system.group.administrator","permissions":1632},"stats":{"size":20465},"mimeType":"text/javascript","binary":false,"modifiedAt":1641896457331},"lib/css/iob/selectID.css":{"acl":{"owner":"system.user.admin","ownerGroup":"system.group.administrator","permissions":1632},"stats":{"size":10448},"mimeType":"text/css","binary":false,"modifiedAt":1641896457397},"lib/css/fancytree/ui.fancytree.min.css":{"acl":{"owner":"system.user.admin","ownerGroup":"system.group.administrator","permissions":1632},"stats":{"size":20395},"mimeType":"text/css","binary":false,"modifiedAt":1641896457462},"lib/css/fancytree/ui.fancytree.min-win7.css":{"acl":{"owner":"system.user.admin","ownerGroup":"system.group.administrator","permissions":1632},"stats":{"size":14380},"mimeType":"text/css","binary":false,"modifiedAt":1641896457528},"lib/css/fancytree/ui.fancytree.jquery.min.css":{"acl":{"owner":"system.user.admin","ownerGroup":"system.group.administrator","permissions":1632},"stats":{"size":5514},"mimeType":"text/css","binary":false,"modifiedAt":1641896457604},"lib/css/fancytree/state.png":{"acl":{"owner":"system.user.admin","ownerGroup":"system.group.administrator","permissions":1632},"stats":{"size":1414},"mimeType":"image/png","binary":true,"modifiedAt":1641896457669},"lib/css/fancytree/loading.gif":{"acl":{"owner":"system.user.admin","ownerGroup":"system.group.administrator","permissions":1632},"stats":{"size":3234},"mimeType":"image/gif","binary":true,"modifiedAt":1641896457735},"lib/css/fancytree/icons.gif":{"acl":{"owner":"system.user.admin","ownerGroup":"system.group.administrator","permissions":1632},"stats":{"size":5492},"mimeType":"image/gif","binary":true,"modifiedAt":1641896457801},"lib/css/fancytree/device.png":{"acl":{"owner":"system.user.admin","ownerGroup":"system.group.administrator","permissions":1632},"stats":{"size":1446},"mimeType":"image/png","binary":true,"modifiedAt":1641896457867},"lib/css/fancytree/channel.png":{"acl":{"owner":"system.user.admin","ownerGroup":"system.group.administrator","permissions":1632},"stats":{"size":1290},"mimeType":"image/png","binary":true,"modifiedAt":1641896457931},"lib/css/bootstrap.min.css":{"acl":{"owner":"system.user.admin","ownerGroup":"system.group.administrator","permissions":1632},"stats":{"size":117150},"mimeType":"text/css","binary":false,"modifiedAt":1641896457998},"index.html":{"acl":{"owner":"system.user.admin","ownerGroup":"system.group.administrator","permissions":1632},"stats":{"size":7009},"mimeType":"text/html","binary":false,"modifiedAt":1641896458073},"admin/img/admin.png":{"acl":{"owner":"system.user.admin","ownerGroup":"system.group.administrator","permissions":1632},"stats":{"size":21804},"mimeType":"image/png","binary":true,"modifiedAt":1641896458139}}